Workbook

Sheet Оглавление
A2: Оглавление
A4: № п/п | B4: Наименование листов EXCEL-файла | C4: Информация на листе
A5: 1 | B5: Общие сведения | C5: Общие сведения об организации. Справка по использованию (вспомогательный лист)
A6: 2 | B6: Заголовочная часть | C6: Заголовочная часть
A7: 3 | B7: Баланс | C7: Бухгалтерский баланс
A8: 4 | B8: Финансовый результат | C8: Отчет о финансовых результатах
A9: 5 | B9: Изменение капитала | C9: Отчет об изменениях капитала
A10: 6 | B10: Движение денежных средств | C10: Отчет о движении денежных средств
A11: 7 | B11: Целевое использование | C11: Отчет о целевом использовании средств
C12: ПОЯСНЕНИЯ К БУХГАЛТЕРСКОМУ БАЛАНСУ И ОТЧЕТУ О ФИНАНСОВЫХ РЕЗУЛЬТАТАХ :
A13: 7 | B13: 5.1.1 | C13: Наличие и движение нематериальных активов
A14: 8 | B14: 5.1.2 | C14: Наличие и движение нематериальных активов, созданных организацией
A15: 9 | B15: 5.1.3 | C15: Капитальные вложения в объекты нематериальных активов
A16: 10 | B16: 5.2.1 | C16: Наличие и движение основных средств
A17: 11 | B17: 5.2.2 | C17: Наличие и движение прав пользования активами
A18: 12 | B18: 5.2.3 | C18: Капитальные вложения в объекты основных средств, инвестиционной недвижимости и права пользования активами
A19: 13 | B19: 5.2.4 | C19: Основные средства, в отношении которых имеются ограничения использования
A20: 14 | B20: 5.3.1 | C20: Наличие и движение финансовых вложений
A21: 15 | B21: 5.3.2 | C21: Иное использование финансовых вложений
A22: 16 | B22: 5.4.1 5.4.2 | C22: Наличие и движение запасов. Запасы, в отношении которых имеются ограничения имущественных прав
A23: 17 | B23: 5.5 | C23: Затраты на производство
A24: 18 | B24: 5.6 | C24: Оценочные обязательства
... A27: 21 | B27: Справочники | C27: Технические справочники и дополнительная информация (вспомогательный скрытый лист)

Sheet Общие сведения
B1: Общие сведения
B2: Дата отчетности (в формате DD.MM.YYYY) | D2: 46112 | F2: Лист "Общие сведения" не обязателен к заполнению. Печать листа не требуется.
A3: Файл XML с данными годовой отчетности для отправки в ФНС:
B4: Имя XML-файла (без расширения .xml) | C4: ИдФайл | D4: ="NO_BUHOTCH_" & D7 & "_" & D8 & "_" & D20 & "_" & TEXT(D10,"ГГГГММДД") & "_1" -> NO_BUHOTCH____19000100_1 | F4: (вместо формулы можно написать имя файла)
B5: Версия программы, с пом. которой сформирован XML-файл | C5: ВерсПрог | D5: 4.93 | F5: Версия программы "Налогоплательщик ЮЛ" версии 4.93 или выше (скорректировать)
B6: Версия формата XML | C6: ВерсФорм | D6: 5.10
B7: Идентификатор получателя, которому направляется файл | C7: А | F7: – четырехразрядный код налогового органа (ФНС, которому направляется файл) | H7: "А" и "К" могут совпадать
B8: Идентификатор конечного получателя, для которого предназначена информация из данного файла | C8: К | F8: – четырехразрядный код налогового органа (ФНС, для которого предназначена информация из данного файла)
B9: Код формы отчетности по КНД | C9: КНД | D9: 0710099 | F9: Принимает значение 0710099 для бухгалтерской(финансовой) отчетности
B10: Дата формирования документа (XML-файла) | C10: ДатаДок | F10: Дата формирования XML-файла в формате ДД.ММ.ГГГГ (формулу можно заменить конкретной датой)
B11: Отчетный период | C11: Период | D11: 34 | G11: текстовое поле 2 символа
B12: Отчетный год | C12: ОтчетГод | D12: 2026 | F12: Год в формате ГГГГ
B13: Отчетность подлежит обязательному аудиту | C13: ПрАудит | D13: =IF(MONTH('Общие сведения'!D2)=12,1,0) -> 0 | F13: Принимает значение: 1 – да | 0 – нет | G13: Стоит формула, но можно и руками менять значение
B14: Номер корректировки | C14: НомКорр | D14: 0 | F14: По умолчанию имеет значение 0.
B15: Код по ОКЕИ | C15: ОКЕИ | D15: 384 | F15: Всегда принимает значение: 384 – тыс. рублей
B16: Дата отчетности (число,месяц,год) | D16: =TEXT(D2, "ДД / ММ / ГГГГ") -> 31 / 03 / 2026 | F16: Текстовое поле используется на листах текущего файла
A17: Сведения о налогоплательщике: | F17: Сведения можно заполнить позднее - в Вашей программе "НалогоплательщикЮЛ" или "Контур"
B18: Краткое наименование организации (текст) | F18: Краткое наименование организации, например, ПАО "Газпром"
B19: Код по ОКПО (число) | C19: ОКПО | F19: ОКПО | G19: текстовое поле от 8 до 10 символов
B20: ИНН (число) | C20: ИННЮЛ | F20: ИНН | G20: текстовое поле 10 символов
B21: Организационно-правовая форма (текст) | D21: Общества с ограниченной ответственностью | F21: - см. инф. на листе "Справочники" | G21: По классификатору организационно-правовых форм ОК 028 - 2014 (ОКОПФ)
B22: Код по ОКОПФ (число) | C22: ОКОПФ | D22: =VLOOKUP(D21,Справочники!C168:D180,2,0) -> 12300 | F22: автоматически вычисляется по коду из ячейки D21 | G22: По классификатору организационно-правовых форм ОК 028 - 2014 (ОКОПФ)
B23: Форма собственности (текст) | C23: НаимОрг | D23: Частная собственность | F23: - см. инф. на листе "Справочники" | G23: По классификатору форм собственности ОК 027 - 2014 (ОКФС)
B24: Код по ОКФС (число) | C24: ОКФС | D24: =VLOOKUP(D23,Справочники!C30:D48,2,0) -> 16 | F24: автоматически вычисляется по коду из ячейки D23 | G24: По классификатору форм собственности ОК 027 - 2014 (ОКФС)
B25: Полный адрес (местонахождение) (текст) | C25: АдрМН | F25: Место нахождения (адрес) регистрации организации. Текстовое поле используется на листе "Титульный лист" текущего файла
A26: Сведения об органе, утверждающего бухгалтерскую отчетность: | F26: Сведения можно заполнить позднее - в Вашей программе "НалогоплательщикЮЛ" или "Контур"
B27: Бухгалтерская отчетность подлежит утверждению | D27: =IF(MONTH('Общие сведения'!D2)=12,1,0) -> 0 | F27: Принимает значение: 1 – да | 0 – нет | G27: Стоит формула, но можно и руками менять значение
B28: Наименование органа, утверждающего бухгалтерскую отчетность | F28: Текстовое поле
A29: Сведения о аудиторе:
B30: Наименование аудиторской организации, проводившей обязательный аудит | C30: НаимОрг | F30: Текстовое поле, например, Общество с ограниченной ответственностью "Финансовые и бухгалтерские консультанты"
B31: Идентификационный номер налогоплательщика (ИНН) аудиторской организации | C31: ИННЮЛ | F31: ИНН | G31: текстовое поле 10 символов
B32: Основной государственный регистрационный номер (ОГРН) аудиторской организации | C32: ОГРН | F32: ОГРН | G32: текстовое поле 13 символов
A33: Подписант (1-руководитель, 2-уполномоченный представитель): | D33: 1 | F33: Сведения можно заполнить позднее - в Вашей программе "НалогоплательщикЮЛ" или "Контур"
B34: Наим. должности (Генеральный директор, Руководитель, ... ) | C34: Фамилия
C35: Имя
C36: Отчетсво
F37: Лист "Общие сведения" вспомогательный. Не для печати!
B38: Файл содержит шаблоны для заполнения отчетных форм в соответствии с ФСБУ 4/2023 "Бухгалтерская (финансовая) отчетность"
B41: Для годовой отчетности формирование XML-файла актуально для всех организаций:
B42: В соответствии с Федеральным законом от 28.11.2018 г. № 444-ФЗ «О внесении изменений в Федеральный закон
B43: «О бухгалтерском учете» с 01.01.2020 вступают в силу новые правила представления организациями обязательного
B44: экземпляра бухгалтерской (финансовой) отчетности.
B45: В соответствии с новыми правилами обязательный экземпляр отчетности представляется экономическим
B46: субъектом в виде электронного документа по телекоммуникационным каналам связи через оператора электронного
B47: документооборота, являющегося российской организацией и соответствующего требованиям,
B48: утверждаемым федеральным органом исполнительной власти, уполномоченным по контролю и надзору в области
B49: налогов и сборов (далее - ФНС).
B50: При этом форматы представления обязательного экземпляра отчетности и аудиторского заключения о ней
B51: в виде электронных документов, порядок представления отчетности и аудиторского заключения также утверждаются ФНС.
... B63: EXCEL-строкам и графам. Вместо удаления строк/граф необходимо их скрыть.

Sheet Справочники
C2: Справочники и дополнительная информация.
C3: Лист "Справочники" вспомогательный. Не для печати!
A5: Комментарии для заполнения наименования XML-файла на листе "Общие сведения":
B7: Имя файла XML cодержит (повторяет) имя XML-файла (без расширения .xml), который будет сформирован в результате
B8: экспорта данных из текущего файла.
B9: Имя файла заполняется непосредственно перед экспортом заполненного текущего файла в формат XML.
B11: Имя файла XML обмена должно иметь следующий вид:
C12: R_Т_A_K_О_GGGGMMDD_N, где:
C13: R_Т – префикс, принимающий значение NO_BUHOTCH;
C14: A_K – идентификатор получателя информации, где: A – идентификатор получателя, которому направляется файл обмена, K – идентификатор конечного получателя, для которого предназначена информация из данного файла обмена . Каждый из идентификаторов (A и K) имеет вид для налоговых органов – четырехразрядный код (код налогового органа в соответствии с классификатором «Система обозначения налоговых органов» (СОНО);
C16: О – идентификатор отправителя информации, имеет вид:
C17: для организаций - девятнадцатиразрядный код (идентификационный номер налогоплательщика (далее - ИНН) и код причины постановки на учет (далее - КПП) организации (обособленного подразделения
C18: GGGG – год формирования передаваемого файла, MM – месяц, DD – день;
C19: N – идентификационный номер файла (длина – от 1 до 36 знаков. Идентификационный номер файла должен обеспечивать уникальность файла).
C20: Расширение имени файла – xml. Расширение имени файла может указываться как строчными, так и прописными буквами
A22: Код отчетного периода на листе "Общие сведения":
C23: 34 – год |
C24: 90 – год при реорганизации (ликвидации) организации (ликвидационная, заключительная отчетность) |
C25: 94 – год при реорганизации (ликвидации) организации (промежуточная, вступительная отчетность)
A27: Форма собственности (по ОКФС)
A28: Код позиции | B28: Код родительской позиции | C28: Форма собственности
A29: 10 | C29: РОССИЙСКАЯ СОБСТВЕННОСТЬ | D29: 10
A30: 11 | B30: 10 | C30: Государственная собственность | D30: 11
A31: 12 | B31: 11 | C31: Федеральная собственность | D31: 12
A32: 13 | B32: 11 | C32: Собственность субъектов Российской Федерации | D32: 13
A33: 14 | B33: 10 | C33: Муниципальная собственность | D33: 14
A34: 16 | B34: 10 | C34: Частная собственность | D34: 16
A35: 18 | B35: 10 | C35: Собственность российских граждан, постоянно проживающих за границей | D35: 18
A36: 19 | B36: 10 | C36: Собственность потребительской кооперации | D36: 19
A37: 15 | B37: 10 | C37: Собственность общественных и религиозных организаций (объединений) | D37: 15
A38: 50 | B38: 15 | C38: Собственность благотворительных организаций | D38: 50
A39: 51 | B39: 15 | C39: Собственность политических общественных объединений | D39: 51
A40: 52 | B40: 15 | C40: Собственность профессиональных союзов | D40: 52
A41: 53 | B41: 15 | C41: Собственность общественных объединений | D41: 53
... A48: 49 | B48: 17 | C48: Иная смешанная российская собственность | D48: 49
A49: 20 | C49: ИНОСТРАННАЯ СОБСТВЕННОСТЬ | D49: 20
A50: 21 | B50: 20 | C50: Собственность международных организаций | D50: 21
A51: 22 | B51: 20 | C51: Собственность иностранных государств | D51: 22
A52: 23 | B52: 20 | C52: Собственность иностранных юридических лиц | D52: 23
A53: 24 | B53: 20 | C53: Собственность иностранных граждан и лиц без гражданства | D53: 24
A54: 27 | B54: 20 | C54: Смешанная иностранная собственность | D54: 27
A55: 30 | C55: СОВМЕСТНАЯ РОССИЙСКАЯ И ИНОСТРАННАЯ СОБСТВЕННОСТЬ | D55: 30
A56: 31 | B56: 30 | C56: Совместная федеральная и иностранная собственность | D56: 31
A57: 32 | B57: 30 | C57: Совместная собственность субъектов Российской Федерации и иностранная собственность | D57: 32
A58: 33 | B58: 30 | C58: Совместная муниципальная и иностранная собственность | D58: 33
A59: 34 | B59: 30 | C59: Совместная частная и иностранная собственность | D59: 34
A60: 35 | B60: 30 | C60: Совместная собственность общественных и религиозных организаций (объединений) и иностранная собственность | D60: 35
A61: 61 | B61: 10 | C61: Собственность государственных корпораций | D61: 61
C63: Коды регионов
B64: Код | C64: Наименование
B65: 01 | C65: Республика Адыгея
B66: 02 | C66: Республика Башкортостан
B67: 03 | C67: Республика Бурятия
B68: 04 | C68: Республика Алтай (Горный Алтай)
B69: 05 | C69: Республика Дагестан
B70: 06 | C70: Республика Ингушетия
B71: 07 | C71: Кабардино-Балкарская Республика
B72: 08 | C72: Республика Калмыкия
B73: 09 | C73: Республика Карачаево-Черкессия
B74: 10 | C74: Республика Карелия
B75: 11 | C75: Республика Коми
... B149: 95 | C149: Чеченская республика
A152: Общероссийский классификатор организационно-правовых форм (ОКОПФ):
B153: Код | C153: Наименование | D153: Изменить значения можно в ячейке D22 на листе "Общие сведения"
C154: Общество с ограниченной ответственностью / Частная собственность
C155: Публичное акционерное общество / Частная собственность
B156: 41 | C156: Общество с ограниченной ответственностью / Смешанная российская собственность с долей федеральной собственности
C157: Акционерное общество / Частная собственность
C158: Закрытое акционерное общество / Частная собственность
C159: Открытое акционерное общество / Частная собственность
C160: Филиал публичного акционерного общества
C161: Представительство публичного акционерного общества
B162: 20200 | C162: Общественные организации | D162: 20200
B163: 10000 | C163: ОРГАНИЗАЦИОННО-ПРАВОВЫЕ ФОРМЫ ЮРИДИЧЕСКИХ ЛИЦ, ЯВЛЯЮЩИХСЯ КОММЕРЧЕСКИМИ КОРПОРАТИВНЫМИ ОРГАНИЗАЦИЯМИ | D163: 10000
B164: 11000 | C164: Хозяйственные товарищества | D164: 11000
B165: 11051 | C165: Полные товарищества | D165: 11051
B166: 11064 | C166: Товарищества на вере (коммандитные товарищества) | D166: 11064
B167: 12000 | C167: Хозяйственные общества | D167: 12000
B168: 12200 | C168: Акционерные общества | D168: 12200
B169: 12247 | C169: Публичные акционерные общества | D169: 12247
B170: 12267 | C170: Непубличные акционерные общества | D170: 12267
B171: 12300 | C171: Общества с ограниченной ответственностью | D171: 12300
B172: 13000 | C172: Хозяйственные партнерства | D172: 13000
B173: 14000 | C173: Производственные кооперативы (артели) | D173: 14000
... B287: 75505 | C287: Общественные учреждения | D287: 75505

Sheet Заголовочная часть
B3: Бухгалтерская отчетность | DO3: Лист заполняется автоматически на основании данных листа "Общие сведения"
B4: ="за " & IF(MONTH('Общие сведения'!D2)=3, "январь - март " & YEAR('Общие сведения'!D2) & " года", IF(MONTH('Общие сведения'!D2)=6, "январь - июнь " & YEAR('Общие сведения'!D2) & " года", IF(MONTH('Общие сведения'!D2)=9, "январь - сентябрь " & YEAR('Общие сведения'!D2) & " года", YEAR('Общие сведения'!D2) & " год"))) -> за январь - март 2026 года
B6: Организация | Q6: =IF('Общие сведения'!D18<>"",'Общие сведения'!D18,"") | BY6: по ОКПО | CN6: =IF('Общие сведения'!D19<>"",'Общие сведения'!D19,"")
B7: Идентификационный номер налогоплательщика | BY7: ИНН | CN7: =IF('Общие сведения'!D20<>"",'Общие сведения'!D20,"")
B8: Организационно-правовая форма | BY8: по ОКОПФ | CN8: =IF('Общие сведения'!D22<>"",'Общие сведения'!D22,"") -> 12300
B9: =IF('Общие сведения'!D21<>"",'Общие сведения'!D21,"") -> Общества с ограниченной ответственностью
B10: Форма собственности | BY10: по ОКФС | CN10: =IF('Общие сведения'!D24<>"",'Общие сведения'!D24,"") -> 16
B11: =IF('Общие сведения'!D23<>"",'Общие сведения'!D23,"") -> Частная собственность
B13: Адрес в пределах места нахождения
B14: =IF('Общие сведения'!D25<>"",'Общие сведения'!D25,"")
B17: Бухгалтерская отчетность подлежит обязательному аудиту | CH17: =IF('Общие сведения'!D13=1,"V","") | CK17: ДА | CR17: =IF('Общие сведения'!D13=0,"V","") -> V | CU17: НЕТ
B19: Наименование аудиторской организации, проводившей обязательный аудит
B20: =IF('Общие сведения'!D30<>"",'Общие сведения'!D30,"")
B23: Идентификационный номер налогоплательщика аудиторской организации | BY23: ИНН | CG23: =IF('Общие сведения'!D31<>"",'Общие сведения'!D31,"")
B24: Основной государственный регистрационный номер аудиторской организации | BY24: ОГРН | CG24: =IF('Общие сведения'!D32<>"",'Общие сведения'!D32,"")
B27: Бухгалтерская отчетность подлежит утверждению | CH27: =IF('Общие сведения'!D27=1,"V","") | CK27: ДА | CR27: =IF('Общие сведения'!D27=0,"V","") -> V | CU27: НЕТ
B29: Наименование органа, утверждающего бухгалтерскую отчетность
B30: =IF('Общие сведения'!D28<>"",'Общие сведения'!D28,"")

Sheet Баланс
A1: Б у х г а л т е р с к и й б а л а н с
A2: ="на " & DAY('Общие сведения'!D2) & CHOOSE(MONTH('Общие сведения'!D2), " января ", " февраля ", " марта ", " апреля ", " мая ", " июня ", " июля ", " августа ", " сентября ", " октября ", " ноября ", " декабря ") & YEAR('Общие сведения'!D2) & " года" -> на 31 марта 2026 года | E2: Коды | J2: форма 1
C3: Форма по ОКУД | E3: 0710001
B4: Отчетная дата (число,месяц,год) | E4: =" " & 'Общие сведения'!D16 -> 31 / 03 / 2026 | I4: После автоматического переса данных в текущий файл Excel любые формулы, а также значения ячеек и настройки форматирования могут быть при необходимости скорректированы. Изменять структуру отчетных таблиц (удалять и добавлять строки и графы) не рекомендуется. Вместо удаления строк необходимо их скрыть.
A5: =" Организация " & 'Общие сведения'!D18 -> Организация | D5: по ОКПО | E5: =" " & 'Общие сведения'!$D19
A9: Единица измерения: тыс.руб. | D9: по ОКЕИ | E9: =" " & 'Общие сведения'!D15 -> 384
A17: Пояс-нения | B17: Наименование показателя | C17: Код показателя | D17: ="На " & DAY('Общие сведения'!$D$2) & CHOOSE(MONTH('Общие сведения'!$D$2), " января ", " февраля ", " марта ", " апреля ", " мая ", " июня ", " июля ", " августа ", " сентября ", " октября ", " ноября ", " декабря ") & " " & YEAR('Общие сведения'!$D$2) & " г." -> На 31 марта 2026 г. | E17: ="На 31 декабря " & YEAR('Общие сведения'!$D$2)-1 & " г." -> На 31 декабря 2025 г. | F17: ="На 31 декабря " & YEAR('Общие сведения'!$D$2)-2 & " г." -> На 31 декабря 2024 г.
B18: Код АСКО | D18: D | E18: E | F18: F
A19: АКТИВ
B20: I. ВНЕОБОРОТНЫЕ АКТИВЫ
B21: Нематериальные активы | C21: 1110
B22: права на объекты интеллектуальной собственности | C22: 1111
B24: прочие | C24: 1119
B26: Нематериальные поисковые активы | C26: 1130
B27: Материальные поисковые активы | C27: 1140
B28: Основные средства | C28: 1150
B29: объекты основных средств | C29: 1151
B30: капитальные вложения | C30: 1152
B31: права пользования активами | C31: 1153
B32: Инвестиционная недвижимость | C32: 1160
B33: Финансовые вложения | C33: 1170
B34: инвестиции в дочерние организации | C34: 1171
... B44: Итого по разделу I | C44: 1100
D46: Форма 0710001 с.2
A47: Пояс-нения | B47: Наименование показателя | C47: Код показателя | D47: =$D$17 -> На 31 марта 2026 г. | E47: =$E$17 -> На 31 декабря 2025 г. | F47: =$F$17 -> На 31 декабря 2024 г.
A48: АКТИВ
B49: II. ОБОРОТНЫЕ АКТИВЫ
B50: Запасы | C50: 1210
B51: сырье, материалы и другие аналогичные ценности | C51: 1211
B52: затраты в незавершенном производстве | C52: 1212
B53: готовая продукция и товары для перепродажи | C53: 1213
B54: товары отгруженные | C54: 1214
B55: Долгосрочные активы к продаже | C55: 1215
B56: Налог на добавленную стоимость по приобретенным ценностям | C56: 1220
B57: Дебиторская задолженность | C57: 1230
B59: покупатели и заказчики | C59: 1232
B60: авансы выданные | C60: 1233
B66: прочие дебиторы | C66: 1239
B67: Финансовые вложения (за исключением денежных эквивалентов) | C67: 1240
... B77: БАЛАНС | C77: 1600
D88: Форма 0710001 с.2
A89: Пояс-нения | B89: Наименование показателя | C89: Код показателя | D89: =$D$17 -> На 31 марта 2026 г. | E89: =$E$17 -> На 31 декабря 2025 г. | F89: =$F$17 -> На 31 декабря 2024 г.
A90: ПАССИВ
B91: III. КАПИТАЛ
B92: Уставный капитал | C92: 1310
B93: Собственные акции (доли), принадлежащие обществу, задолженность акционеров (участников) по оплате акций (долей) | C93: 1320
B94: Накопленная дооценка внеоборотных активов | C94: 1340
B95: Добавочный капитал (без накопленной дооценки) | C95: 1350
B96: бессрочные облигации и займы | C96: 1351
B97: Резервный капитал | C97: 1360
B98: Нераспределенная прибыль (непокрытый убыток) | C98: 1370
B100: Итого по разделу III | C100: 1300
B111: IV. ДОЛГОСРОЧНЫЕ ОБЯЗАТЕЛЬСТВА
B112: Заемные средства | C112: 1410
B113: долгосрочные кредиты | C113: 1411
B114: долгосрочные займы | C114: 1412
B115: Отложенные налоговые обязательства | C115: 1420
B116: Оценочные обязательства | C116: 1430
B117: Прочие долгосрочные обязательства | C117: 1450
B118: кредиторская задолженность | C118: 1451
B121: обязательства по аренде | C121: 1455
B122: Итого по разделу IV | C122: 1400
B131: V. КРАТКОСРОЧНЫЕ ОБЯЗАТЕЛЬСТВА
B132: Заемные средства | C132: 1510
B133: краткосрочные кредиты | C133: 1511
B134: краткосрочные займы | C134: 1512
B135: текущая часть долгосрочных кредитов и займов | C135: 1513
B136: Кредиторская задолженность | C136: 1520
B137: поставщики и подрядчики | C137: 1521
B138: задолженность перед персоналом организации | C138: 1522
B139: задолженность по страховым взносам | C139: 1523
B140: задолженность по налогам и сборам | C140: 1524
B143: авансы полученные | C143: 1525
B144: задолженность перед акционерами (участниками) по выплате доходов | C144: 1526
B145: прочие кредиторы | C145: 1529
... B151: БАЛАНС | C151: 1700
B152: СПРАВКА О НАЛИЧИИ ЦЕННОСТЕЙ, УЧИТЫВАЕМЫХ НА ЗАБАЛАНСОВЫХ СЧЕТАХ
B153: Наименование показателя
B154: 1
B155: Арендованные основные средства
B156: в том числе по лизингу
B157: Ликвидированные скважины, находящиеся на лицензионных участках
B158: Товарно-материальные ценности,принятые на ответственное хранение
B159: Материалы, принятые в переработку
B160: Товары, принятые на комиссию
B161: Оборудование, принятое для монтажа
B162: Списанная в убыток задолженность неплатежеспособных дебиторов
B163: Расходы по договорам строительного подряда, понесенные за период с начала исполнения договора
B164: Обеспечения обязательств и платежей полученные
B165: Обеспечения обязательств и платежей выданные
B166: Износ жилищного фонда
... B169: Стоимость выручки по экспортным контрактам, переданная в залог
B172: ='Общие сведения'!B34 -> Наим. должности (Генеральный директор, Руководитель, ... )
B173: (наименование должности)
D176: ='Общие сведения'!D34 -> 0
B177: (подпись) | D177: (расшифровка подписи)
B179: "_____" ________________________ 2026 г.

Sheet Финансовый результат
A1: Отчет о финансовых результатах
A2: ="за " & IF(MONTH('Общие сведения'!D2)=3, "январь - март " & YEAR('Общие сведения'!D2) & " года", IF(MONTH('Общие сведения'!D2)=6, "январь - июнь " & YEAR('Общие сведения'!D2) & " года", IF(MONTH('Общие сведения'!D2)=9, "январь - сентябрь " & YEAR('Общие сведения'!D2) & " года", YEAR('Общие сведения'!D2) & " год"))) -> за январь - март 2026 года
E4: Коды | H4: форма 2
C5: Форма по ОКУД | E5: 0710002
B6: Отчетная дата (число,месяц,год) | E6: =" " & 'Общие сведения'!D16 -> 31 / 03 / 2026
A7: =" Организация " & 'Общие сведения'!D18 -> Организация | D7: по ОКПО | E7: =" " & 'Общие сведения'!D19
A11: Единица измерения: тыс.руб. | D11: по ОКЕИ | E11: =" " & 'Общие сведения'!D15 -> 384
A13: Пояс-нения | B13: Наименование показателя | C13: Код показателя | D13: ="За " & IF(MONTH('Общие сведения'!D2)=3, "январь-март " & YEAR('Общие сведения'!D2) & " г.", IF(MONTH('Общие сведения'!D2)=6, "январь-июнь " & YEAR('Общие сведения'!D2) & " г.", IF(MONTH('Общие сведения'!D2)=9, "январь-сентябрь " & YEAR('Общие сведения'!D2) & " г.", YEAR('Общие сведения'!D2) & " г."))) -> За январь-март 2026 г. | E13: ="За " & IF(MONTH('Общие сведения'!D2)=3, "январь-март " & YEAR('Общие сведения'!D2)-1 & " г.", IF(MONTH('Общие сведения'!D2)=6, "январь-июнь " & YEAR('Общие сведения'!D2)-1 & " г.", IF(MONTH('Общие сведения'!D2)=9, "январь-сентябрь " & YEAR('Общие сведения'!D2)-1 & " г.", YEAR('Общие сведения'!D2)-1 & " г."))) -> За январь-март 2025 г.
B14: Код АСКО | D14: D | E14: E
B15: Выручка, в т.ч.: | C15: 2110
C16: 2111
C17: 2112
C18: 2113
C19: 2114
C20: 2115
C21: 2116
C22: 2117
B23: прочее | C23: 2118
B24: Себестоимость продаж, в т.ч.: | C24: 2120
C25: 2121
C26: 2122
C27: 2123
C28: 2124
C29: 2125
C30: 2126
C31: 2127
B32: прочее | C32: 2128
B33: Валовая прибыль (убыток) | C33: 2100
B34: Коммерческие расходы | C34: 2210
B35: Управленческие расходы | C35: 2220
B36: Прибыль (убыток) от продаж | C36: 2200
B37: Доходы от участия в других организациях | C37: 2310
B38: Проценты к получению | C38: 2320
B39: Проценты к уплате | C39: 2330
D40: Форма 0710002 с.2
A41: Пояс-нения | B41: Наименование показателя | C41: Код показателя | D41: =D13 -> За январь-март 2026 г. | E41: =E13 -> За январь-март 2025 г.
B42: Прочие доходы | C42: 2340
B43: Прочие расходы | C43: 2350
B45: Прибыль (убыток) от продолжающейся деятельности до налогообложения | C45: 2300
B46: Налог на прибыль организаций, в т.ч.: | C46: 2410
B47: текущий налог на прибыль организаций | C47: 2411
B48: отложенный налог на прибыль организаций | C48: 2412
B49: налог на прибыль прошлых лет | C49: 2413
B52: Прибыль (убыток) от прекращаемой деятельности (за вычетом относящегося к ней налога на прибыль организаций) | C52: 2420
B53: Прочее | C53: 2460
B57: Чистая прибыль (убыток) | C57: 2400
B60: СПРАВОЧНО:
B61: Результат переоценки внеоборотных активов, не включаемый в чистую прибыль (убыток) | C61: 2510
B62: Результат прочих операций, не включаемый в чистую прибыль (убыток) | C62: 2520
B64: Налог на прибыль организаций, относящийся к результатам переоценки внеоборотных активов и прочих операций, не включаемых в чистую прибыль (убыток) | C64: 2530
B65: Совокупный финансовый результат | C65: 2500
B66: Базовая прибыль (убыток) на акцию, руб. коп. | C66: 2900
B67: Разводненная прибыль (убыток) на акцию, руб. коп. | C67: 2910
B69: ='Общие сведения'!B34 -> Наим. должности (Генеральный директор, Руководитель, ... )
B70: (наименование должности)
D73: ='Общие сведения'!D34 -> 0
B74: (подпись) | D74: (расшифровка подписи)
B76: "_____" ________________________ 2026 г.
A77: (НЕ ДЛЯ ПЕЧАТИ) | B77: Вычисляемые значения только для экспорта в XML-файл: | C77: 2460+ 2465 | D77: =D53+D54 -> 0 | E77: =E53+E54 -> 0
B78: Чтобы в XML-файле строка 2465 суммируются к строке 2460

Sheet Изменение капитала
A1: Отчет об изменениях капитала
A2: ="за " & IF(MONTH('Общие сведения'!D2)=3, "январь - март " & YEAR('Общие сведения'!D2) & " года", IF(MONTH('Общие сведения'!D2)=6, "январь - июнь " & YEAR('Общие сведения'!D2) & " года", IF(MONTH('Общие сведения'!D2)=9, "январь - сентябрь " & YEAR('Общие сведения'!D2) & " года", YEAR('Общие сведения'!D2) & " год"))) -> за январь - март 2026 года
K5: КОДЫ
H6: Форма по ОКУД | K6: 0710004 | M6: форма 3
G7: Отчетная дата (число,месяц,год) | K7: =" " & 'Общие сведения'!D16 -> 31 / 03 / 2026
A8: =" Организация " & 'Общие сведения'!D18 -> Организация | H8: по ОКПО | K8: =" " & 'Общие сведения'!D19
A12: Единица измерения: тыс.руб. | H12: по ОКЕИ | K12: =" " & 'Общие сведения'!D15 -> 384
A14: Пояс-нения | B14: Наименование показателя | C14: Код показателя | D14: Уставный капитал | E14: Собственные акции (доли), принадлежащие обществу, задолженность акционеров (участников) по оплате акций (долей) | F14: Накопленная дооценка внеоборотных активов | G14: Добавочный капитал (без накопленной дооценки) | H14: Резервный капитал | I14: Нераспределенная прибыль (непокрытый убыток) | K14: Итого
B15: Код АСКО | D15: D | E15: E | F15: F | G15: G | H15: H | I15: I | J15: J | K15: K
B16: ="На 31 декабря " & YEAR('Общие сведения'!$D$2)-2 & " г." -> На 31 декабря 2024 г. | C16: 3100 | F16: - | K16: =SUM(D16:J16) -> 0
B17: Корректировка в связи с: изменением учетной политики | C17: 3110 | D17: - | E17: - | F17: - | K17: =SUM(D17:J17) -> 0
B18: исправлением ошибок | C18: 3120 | D18: - | E18: - | F18: - | K18: =SUM(D18:J18) -> 0
B19: ="На 31 декабря " & YEAR('Общие сведения'!$D$2)-2 & " г. после корректировки" -> На 31 декабря 2024 г. после корректировки | C19: 3101 | F19: - | K19: =SUM(D19:J19) -> 0
B20: ="за " & IF(MONTH('Общие сведения'!D2)=3, "январь - март " & YEAR('Общие сведения'!D2)-1 & " года Чистая прибыль (убыток) ", IF(MONTH('Общие сведения'!D2)=6, "январь - июнь " & YEAR('Общие сведения'!D2)-1 & " года Чистая прибыль (убыток) ", IF(MONTH('Общие сведения'!D2)=9, "январь - сентябрь " & YEAR('Общие сведения'!D2)-1 & " года Чистая прибыль (убыток) ", YEAR('Общие сведения'!D2)-1 & " год Чистая прибыль (убыток) "))) -> за январь - март 2025 года Чистая прибыль (убыток) | C20: 3211 | D20: - | E20: - | F20: - | G20: - | H20: - | K20: =SUM(D20:J20) -> 0
B21: Переоценка внеоборотных активов | C21: 3212 | D21: - | E21: - | F21: - | G21: - | H21: - | I21: - | K21: =SUM(D21:J21) -> 0
B22: Дивиденды | C22: 3227 | D22: - | E22: - | F22: - | G22: - | H22: - | K22: =SUM(D22:J22) -> 0
B23: Иные изменения за счет операций с собственниками (за исключением дивидендов) - всего | C23: 3230 | D23: =SUM(D24:D30) -> 0 | E23: =SUM(E24:E30) -> 0 | F23: =SUM(F24:F30) -> 0 | G23: =SUM(G24:G30) -> 0 | H23: =SUM(H24:H30) -> 0 | I23: =SUM(I24:I30) -> 0 | K23: =SUM(D23:J23) -> 0
B24: в том числе:
B25: дополнительный выпуск акций | C25: 3231 | E25: - | F25: - | H25: - | I25: - | K25: =SUM(D25:J25) -> 0
B26: увеличение (уменьшение) номинальной стоимости акций (долей) | C26: 3232 | E26: - | F26: - | H26: - | K26: =SUM(D26:J26) -> 0
B27: выкуп собственных акций (долей) | C27: 3233 | D27: - | F27: - | G27: - | H27: - | I27: - | K27: =SUM(D27:J27) -> 0
B28: уменьшение количества акций (погашение долей) | C28: 3234 | F28: - | G28: - | H28: - | I28: - | K28: =SUM(D28:J28) -> 0
B29: вклады в имущество | C29: 3235 | D29: - | E29: - | F29: - | H29: - | I29: - | K29: =SUM(D29:J29) -> 0
B30: прочее | C30: 3239 | D30: - | F30: - | G30: - | H30: - | K30: =SUM(D30:J30) -> 0
B32: Реорганизация юридического лица | C32: 3216 | F32: - | K32: =SUM(D32:J32) -> 0
B33: Иные изменения - всего | C33: 3240 | D33: =SUM(D34:D36) -> 0 | E33: =SUM(E34:E36) -> 0 | F33: =SUM(F34:F36) -> 0 | G33: =SUM(G34:G36) -> 0 | H33: =SUM(H34:H36) -> 0 | I33: =SUM(I34:I36) -> 0 | K33: =SUM(D33:J33) -> 0
B34: в том числе: | K34: =SUM(D34:J34) -> 0
B35: операции, связанные с бессрочными облигациями и займами | C35: 3245 | D35: - | E35: - | F35: - | H35: - | K35: =SUM(D35:J35) -> 0
B36: прочее | C36: 3249 | F36: - | K36: =SUM(D36:J36) -> 0
K37: =SUM(D37:J37) -> 0
K38: =SUM(D38:J38) -> 0
B39: ="На " & DAY('Общие сведения'!$D$2) & CHOOSE(MONTH('Общие сведения'!$D$2), " января ", " февраля ", " марта ", " апреля ", " мая ", " июня ", " июля ", " августа ", " сентября ", " октября ", " ноября ", " декабря ") & "" & YEAR('Общие сведения'!$D$2)-1 & " г." -> На 31 марта 2025 г. | C39: 3250 | D39: =D19+D23+D32+D33 -> 0 | E39: =E19+E23+E32+E33 -> 0 | F39: =F23+F33 -> 0 | G39: =G19+G23+G32+G33 -> 0 | H39: =H19+H23+H32+H33 -> 0 | I39: =I19+I20+I22+I23+I32+I33 -> 0 | K39: =SUM(D39:J39) -> 0
E41: Форма 0710004 с.2
A42: Пояс-нения | B42: Наименование показателя | C42: Код показателя | D42: Уставный капитал | E42: Собственные акции (доли), принадлежащие обществу, задолженность акционеров (участников) по оплате акций (долей) | F42: Накопленная дооценка внеоборотных активов | G42: Добавочный капитал (без накопленной дооценки) | H42: Резервный капитал | I42: Нераспределенная прибыль (непокрытый убыток) | K42: Итого
B43: ="На 31 декабря " & YEAR('Общие сведения'!$D$2)-1 & " г." -> На 31 декабря 2025 г. | C43: 3200 | F43: - | K43: =SUM(D43:J43) -> 0
B44: Корректировка в связи с: изменением учетной политики | C44: 3210 | D44: - | E44: - | F44: - | K44: =SUM(D44:J44) -> 0
B45: исправлением ошибок | C45: 3220 | D45: - | E45: - | F45: - | K45: =SUM(D45:J45) -> 0
B48: ="На 31 декабря " & YEAR('Общие сведения'!$D$2)-1 & " г. после корректировки" -> На 31 декабря 2025 г. после корректировки | C48: 3201 | F48: - | K48: =SUM(D48:J48) -> 0
B49: ="за " & IF(MONTH('Общие сведения'!D2)=3, "январь - март " & YEAR('Общие сведения'!D2) & " года Чистая прибыль (убыток) ", IF(MONTH('Общие сведения'!D2)=6, "январь - июнь " & YEAR('Общие сведения'!D2) & " года Чистая прибыль (убыток) ", IF(MONTH('Общие сведения'!D2)=9, "январь - сентябрь " & YEAR('Общие сведения'!D2) & " года Чистая прибыль (убыток) ", YEAR('Общие сведения'!D2) & " год Чистая прибыль (убыток) "))) -> за январь - март 2026 года Чистая прибыль (убыток) | C49: 3311 | D49: - | E49: - | F49: - | G49: - | H49: - | K49: =SUM(D49:J49) -> 0
B50: Переоценка внеоборотных активов | C50: 3312 | D50: - | E50: - | F50: - | G50: - | H50: - | I50: - | K50: =SUM(D50:J50) -> 0
B51: Дивиденды | C51: 3327 | D51: - | E51: - | F51: - | G51: - | H51: - | K51: =SUM(D51:J51) -> 0
B52: Иные изменения за счет операций с собственниками (за исключением дивидендов) - всего | C52: 3330 | D52: =SUM(D53:D59) -> 0 | E52: =SUM(E53:E59) -> 0 | F52: =SUM(F53:F59) -> 0 | G52: =SUM(G53:G59) -> 0 | H52: =SUM(H53:H59) -> 0 | I52: =SUM(I53:I59) -> 0 | K52: =SUM(D52:J52) -> 0
B53: в том числе:
B54: дополнительный выпуск акций | C54: 3331 | E54: - | F54: - | H54: - | I54: - | K54: =SUM(D54:J54) -> 0
B55: увеличение (уменьшение) номинальной стоимости акций (долей) | C55: 3332 | E55: - | F55: - | H55: - | K55: =SUM(D55:J55) -> 0
B56: выкуп собственных акций (долей) | C56: 3333 | D56: - | F56: - | G56: - | H56: - | I56: - | K56: =SUM(D56:J56) -> 0
B57: уменьшение количества акций (погашение долей) | C57: 3334 | F57: - | G57: - | H57: - | I57: - | K57: =SUM(D57:J57) -> 0
B58: вклады в имущество | C58: 3335 | D58: - | E58: - | F58: - | H58: - | I58: - | K58: =SUM(D58:J58) -> 0
B59: прочее | C59: 3339 | D59: - | F59: - | G59: - | H59: - | K59: =SUM(D59:J59) -> 0
B69: Реорганизация юридического лица | C69: 3316 | F69: - | K69: =SUM(D69:J69) -> 0
B70: Иные изменения - всего | C70: 3340 | D70: =SUM(D71:D73) -> 0 | E70: =SUM(E71:E73) -> 0 | F70: =SUM(F71:F73) -> 0 | G70: =SUM(G71:G73) -> 0 | H70: =SUM(H71:H73) -> 0 | I70: =SUM(I71:I73) -> 0 | K70: =SUM(D70:J70) -> 0
B71: в том числе: | K71: =SUM(D71:J71) -> 0
B72: операции, связанные с бессрочными облигациями и займами | C72: 3345 | D72: - | E72: - | F72: - | H72: - | K72: =SUM(D72:J72) -> 0
B73: прочее | C73: 3349 | F73: - | K73: =SUM(D73:J73) -> 0
K74: =SUM(D74:J74) -> 0
K75: =SUM(D75:J75) -> 0
B76: ="На " & DAY('Общие сведения'!$D$2) & CHOOSE(MONTH('Общие сведения'!$D$2), " января ", " февраля ", " марта ", " апреля ", " мая ", " июня ", " июля ", " августа ", " сентября ", " октября ", " ноября ", " декабря ") & "" & YEAR('Общие сведения'!$D$2) & " г." -> На 31 марта 2026 г. | C76: 3300 | D76: =D48+D52+D69+D70 -> 0 | E76: =E48+E52+E69+E70 -> 0 | F76: =F52+F70 -> 0 | G76: =G48+G52+G69+G70 -> 0 | H76: =H48+H52+H69+H70 -> 0 | I76: =I48+I49+I51+I52+I69+I70 -> 0 | K76: =SUM(D76:J76) -> 0
B78: ='Общие сведения'!B34 -> Наим. должности (Генеральный директор, Руководитель, ... ) | H78: ='Общие сведения'!D34 -> 0
B79: (наименование должности) | E79: (подпись) | H79: (расшифровка подписи)
B82: "_____" ________________________ 2026 г.

Sheet Изм. капитала старый формат
A1: Отчет об изменениях капитала
B2: ="за " & IF(MONTH('Общие сведения'!D2)=3, "январь - март " & YEAR('Общие сведения'!D2) & " года", IF(MONTH('Общие сведения'!D2)=6, "январь - июнь " & YEAR('Общие сведения'!D2) & " года", IF(MONTH('Общие сведения'!D2)=9, "январь - сентябрь " & YEAR('Общие сведения'!D2) & " года", YEAR('Общие сведения'!D2) & " год"))) -> за январь - март 2026 года
J5: КОДЫ
G6: Форма по ОКУД | J6: 710004 | L6: форма 3
F7: Дата (число,месяц,год) | J7: =" " & 'Общие сведения'!D16 -> 31 / 03 / 2026
A8: =" Организация: " & 'Общие сведения'!D18 -> Организация: | G8: по ОКПО | J8: =" " & 'Общие сведения'!D19
A9: Идентификационный номер налогоплательщика | G9: ИНН | J9: =" " & 'Общие сведения'!D20
A10: =" Вид экономической деятельности: " -> Вид экономической деятельности: | G10: по ОКВЭД 2 | J10: =" "
A11: Организационно-правовая форма/форма собственности:
A12: =" " & 'Общие сведения'!D22 -> 12300 | G12: по ОКОПФ/ОКФС | J12: =" " & 'Общие сведения'!D22 & "/" & 'Общие сведения'!D24 -> 12300/16
A13: Единица измерения: тыс.руб. | G13: по ОКЕИ | J13: =" " & 'Общие сведения'!D15 -> 384
A15: 1. Движение капитала
A17: Наименование показателя | B17: Код строки | C17: Уставный капитал | D17: Собственные акции, выкупленные у акционеров | E17: Добавочный капитал | F17: Резервный капитал | G17: Нераспреде-ленная прибыль (непокрытый убыток) | H17: Фонд социальной сферы государственной | I17: Фонд социаль-ной сферы государст-венной | J17: Итого
A18: Величина капитала на 31 декабря 2023 г. | B18: 3100 | C18: 0 | D18: 0 | E18: 0 | F18: 0 | G18: 0 | I18: 0 | J18: =C18+D18+E18+F18+G18+I18 -> 0
A19: Изменения в связи с переоценкой ОС | B19: 3104 | C19: 0 | D19: 0 | F19: 0
A20: Другие изменения вступительного сальдо | B20: 3108
A21: За 2024 год
A22: Увеличение капитала - всего, в том числе: | B22: 3210 | C22: =SUM(C23:C129) -> 0 | D22: =SUM(D23:D129) -> 0 | E22: =SUM(E23:E129) -> 0 | F22: =SUM(F23:F129) -> 0 | G22: =SUM(G23:G129) -> 0 | H22: =SUM(H23:H129) -> 0 | I22: =SUM(I23:I129) -> 0 | J22: =SUM(J23:J129) -> 0
A23: чистая прибыль | B23: 3211 | C23: Х | D23: Х | E23: Х | F23: Х | G23: 0 | H23: 0 | I23: Х | J23: =SUM(C23:I23) -> 0
A24: переоценка имущества | B24: 3212 | C24: Х | D24: Х | E24: 0 | F24: Х | G24: Х | H24: 0 | I24: 0 | J24: =SUM(C24:I24) -> 0
A25: доходы, относящиеся непосредственно на увеличение капитала | B25: 3213 | C25: Х | D25: Х | E25: 0 | F25: Х | G25: 0 | H25: 0 | I25: Х | J25: =SUM(C25:I25) -> 0
A26: дополнительный выпуск акций | B26: 3214 | C26: 0 | D26: Х | E26: 0 | F26: Х | G26: Х | H26: 0 | I26: Х | J26: =SUM(C26:I26) -> 0
A27: увеличение номинальной стоимости акций | B27: 3215 | C27: 0 | D27: Х | E27: 0 | F27: Х | G27: 0 | H27: 0 | I27: Х | J27: =SUM(C27:I27) -> 0
A28: реорганизация юридического лица | B28: 3216 | C28: 0 | D28: 0 | E28: 0 | F28: 0 | G28: 0 | I28: 0 | J28: =SUM(C28:I28) -> 0
A29: выкуп собственных акций | B29: 3217 | C29: Х | D29: 0 | E29: Х | F29: Х | G29: Х | H29: 0 | I29: Х | J29: =SUM(C29:I29) -> 0
A128: операции, связанные с бессрочными облигациями и займами | B128: 3218 | C128: Х | D128: Х | E128: 0 | F128: Х | G128: 0 | I128: Х | J128: =SUM(C128:I128) -> 0
A129: прочее | B129: 3219 | C129: 0 | D129: 0 | E129: 0 | F129: 0 | G129: 0 | I129: Х | J129: =SUM(C129:I129) -> 0
A130: Уменьшение капитала - всего, в том числе: | B130: 3220 | C130: =SUM(C131:C139) -> 0 | D130: =SUM(D131:D139) -> 0 | E130: =SUM(E131:E139) -> 0 | F130: =SUM(F131:F139) -> 0 | G130: =SUM(G131:G139) -> 0 | H130: =SUM(H131:H139) -> 0 | I130: =SUM(I131:I139) -> 0 | J130: =SUM(J131:J139) -> 0
A131: убыток | B131: 3221 | C131: Х | D131: Х | E131: Х | F131: Х | G131: 0 | H131: 0 | I131: Х | J131: =SUM(C131:I131) -> 0
A132: переоценка имущества | B132: 3222 | C132: Х | D132: Х | E132: 0 | F132: Х | G132: Х | H132: 0 | I132: 0 | J132: =SUM(C132:I132) -> 0
A133: расходы, относящиеся непосредственно на уменьшение капитала | B133: 3223 | C133: Х | D133: Х | E133: Х | F133: Х | G133: 0 | H133: 0 | I133: 0 | J133: =SUM(C133:I133) -> 0
A134: уменьшение номинальной стоимости акций | B134: 3224 | C134: 0 | D134: Х | E134: Х | F134: Х | G134: 0 | I134: Х | J134: =SUM(C134:I134) -> 0
A135: уменьшение количества акций | B135: 3225 | C135: 0 | D135: 0 | E135: Х | F135: Х | G135: Х | H135: 0 | I135: Х | J135: =SUM(C135:I135) -> 0
A136: реорганизация юридического лица | B136: 3226 | C136: 0 | D136: 0 | E136: 0 | F136: 0 | G136: 0 | I136: 0 | J136: =SUM(C136:I136) -> 0
A137: дивиденды | B137: 3227 | C137: Х | D137: Х | E137: Х | F137: Х | G137: 0 | I137: Х | J137: =SUM(C137:I137) -> 0
A138: операции, связанные с бессрочными облигациями и займами | B138: 3228 | C138: Х | D138: Х | E138: 0 | F138: Х | G138: 0 | H138: 0 | I138: Х | J138: =SUM(C138:I138) -> 0
A139: прочее | B139: 3229 | C139: 0 | D139: 0 | E139: 0 | F139: 0 | G139: 0 | I139: Х | J139: =SUM(C139:I139) -> 0
D141: Форма 0710004 с.2
A142: Наименование показателя | B142: Код строки | C142: Уставный капитал | D142: Собственные акции, выкупленные у акционеров | E142: Добавочный капитал | F142: Резервный капитал | G142: Нераспреде-ленная прибыль (непокрытый убыток) | H142: Фонд социальной сферы государственной | I142: Фонд социаль-ной сферы государст-венной | J142: Итого
A143: Изменение добавочного капитала | B143: 3230 | C143: Х | D143: Х | E143: 0 | F143: Х | G143: 0 | I143: Х | J143: =SUM(C143:I143) -> 0
A144: Изменение резервного капитала | B144: 3240 | C144: Х | D144: Х | E144: Х | F144: 0 | G144: 0 | I144: Х | J144: =SUM(C144:I144) -> 0
A145: Величина капитала на 31 декабря 2024 г. | B145: 3200 | C145: =C18+C22+C130 -> 0 | D145: =D18+D22+D130 -> 0 | E145: =E18+E22+E130+E143 -> 0 | F145: =F18+F22+F130+F144 -> 0 | G145: =G18+G22+G130+G143+G144 -> 0 | I145: =I18+I22+I130 -> 0 | J145: =J18+J22+J130+J143+J144 -> 0
A146: Изменения в связи с переоценкой ОС | B146: 3204 | C146: 0 | D146: 0 | F146: 0
A147: Другие изменения вступительного сальдо | B147: 3208
A148: За 2025 год
A149: Увеличение капитала - всего, в том числе: | B149: 3310 | C149: =SUM(C150:C158) -> 0 | D149: =SUM(D150:D158) -> 0 | E149: =SUM(E150:E158) -> 0 | F149: =SUM(F150:F158) -> 0 | G149: =SUM(G150:G158) -> 0 | I149: =SUM(I150:I158) -> 0 | J149: =SUM(C149:I149) -> 0
A150: чистая прибыль | B150: 3311 | C150: Х | D150: Х | E150: Х | F150: Х | G150: 0 | I150: Х | J150: =SUM(C150:I150) -> 0
A151: переоценка имущества | B151: 3312 | C151: Х | D151: Х | E151: 0 | F151: Х | G151: Х | I151: 0 | J151: =SUM(C151:I151) -> 0
A152: доходы, относящиеся непосредственно на увеличение капитала | B152: 3313 | C152: Х | D152: Х | E152: 0 | F152: Х | G152: 0 | I152: Х | J152: =SUM(C152:I152) -> 0
A153: дополнительный выпуск акций | B153: 3314 | C153: 0 | D153: Х | E153: 0 | F153: Х | G153: Х | H153: 0 | I153: Х | J153: =SUM(C153:I153) -> 0
A154: увеличение номинальной стоимости акций | B154: 3315 | C154: 0 | D154: Х | E154: 0 | F154: Х | G154: 0 | H154: 0 | I154: Х | J154: =SUM(C154:I154) -> 0
A155: реорганизация юридического лица | B155: 3316 | C155: 0 | D155: 0 | E155: 0 | F155: 0 | G155: 0 | I155: 0 | J155: =SUM(C155:I155) -> 0
A156: выкуп собственных акций | B156: 3317 | C156: Х | D156: 0 | E156: Х | F156: Х | G156: Х | H156: 0 | I156: Х | J156: =SUM(C156:I156) -> 0
A157: операции, связанные с бессрочными облигациями и займами | B157: 3318 | C157: Х | D157: Х | E157: 0 | F157: Х | G157: 0 | I157: Х | J157: =SUM(C157:I157) -> 0
A158: прочее | B158: 3319 | C158: 0 | D158: 0 | E158: 0 | F158: 0 | G158: 0 | I158: 0 | J158: =SUM(C158:I158) -> 0
A159: Уменьшение капитала - всего, в том числе: | B159: 3320 | C159: =SUM(C160:C168) -> 0 | D159: =SUM(D160:D168) -> 0 | E159: =SUM(E160:E168) -> 0 | F159: =SUM(F160:F168) -> 0 | G159: =SUM(G160:G168) -> 0 | H159: =SUM(H160:H168) -> 0 | I159: =SUM(I160:I168) -> 0 | J159: =SUM(C159:I159) -> 0
A160: убыток | B160: 3321 | C160: Х | D160: Х | E160: Х | F160: Х | G160: 0 | I160: Х | J160: =SUM(C160:I160) -> 0
A161: переоценка имущества | B161: 3322 | C161: Х | D161: Х | E161: 0 | F161: Х | G161: Х | I161: 0 | J161: =SUM(C161:I161) -> 0
A162: расходы, относящиеся непосредственно на уменьшение капитала | B162: 3323 | C162: Х | D162: Х | E162: Х | F162: Х | G162: 0 | I162: 0 | J162: =SUM(C162:I162) -> 0
A163: уменьшение номинальной стоимости акций | B163: 3324 | C163: 0 | D163: Х | E163: Х | F163: Х | G163: 0 | I163: Х | J163: =SUM(C163:I163) -> 0
A164: уменьшение количества акций | B164: 3325 | C164: 0 | D164: 0 | E164: Х | F164: Х | G164: Х | H164: 0 | I164: Х | J164: =SUM(C164:I164) -> 0
A165: реорганизация юридического лица | B165: 3326 | C165: 0 | D165: 0 | E165: 0 | F165: 0 | G165: 0 | H165: 0 | I165: 0 | J165: =SUM(C165:I165) -> 0
A166: дивиденды | B166: 3327 | C166: Х | D166: Х | E166: Х | F166: Х | G166: 0 | H166: 0 | I166: Х | J166: =SUM(C166:I166) -> 0
A167: операции, связанные с бессрочными облигациями и займами | B167: 3328 | C167: Х | D167: Х | E167: 0 | F167: Х | G167: 0 | H167: 0 | I167: Х | J167: =SUM(C167:I167) -> 0
A168: прочее | B168: 3329 | C168: 0 | D168: 0 | E168: 0 | F168: 0 | G168: 0 | H168: 0 | I168: Х | J168: =SUM(C168:I168) -> 0
A169: Изменение добавочного капитала | B169: 3330 | C169: Х | D169: Х | E169: 0 | F169: Х | G169: 0 | H169: 0 | I169: Х | J169: =SUM(C169:I169) -> 0
A170: Изменение резервного капитала | B170: 3340 | C170: Х | D170: Х | E170: Х | F170: 0 | G170: 0 | I170: Х | J170: =SUM(C170:I170) -> 0
A171: Величина капитала на 31 декабря 2025 г. | B171: 3300 | C171: =C145+C149+C159 -> 0 | D171: =D145+D149+D159 -> 0 | E171: =E145+E149+E159+E169 -> 0 | F171: =F145+F149+F159+F170 -> 0 | G171: =G145+G149+G159+G169+G170 -> 0 | I171: =I145+I149+I159 -> 0 | J171: =SUM(C171:I171) -> 0

Sheet Коррект. изм.УП старый формат
D1: Форма 0710004 с.3
A3: 2. Корректировки в связи с изменением учетной политики и исправлением ошибок
H4: форма 3_а
A5: Наименование показателя | B5: Код строки | C5: ="На 31 декабря " & YEAR('Общие сведения'!$D$2)-2 & " г." -> На 31 декабря 2024 г. | D5: ="Изменения капитала за " & YEAR('Общие сведения'!$D$2)-1 & " год" -> Изменения капитала за 2025 год | F5: ="На 31 декабря " & YEAR('Общие сведения'!$D$2)-1 & " г." -> На 31 декабря 2025 г.
D6: за счет чистой прибыли (убытка) | E6: за счет иных факторов
A7: 1 | C7: 3 | D7: 4 | E7: 5 | F7: 6
A8: Капитал - всего до корректировок | B8: 3400 | C8: 0 | D8: 0 | E8: 0 | F8: 0
A9: корректировка в связи с:
A10: изменением учетной политики | B10: 3410 | C10: 0 | D10: 0 | E10: 0 | F10: 0
A11: исправлением ошибок | B11: 3420 | C11: 0 | D11: 0 | E11: 0 | F11: 0
A12: после корректировок | B12: 3500 | C12: 0 | D12: 0 | E12: 0 | F12: 0
A13: в том числе:
A14: нераспределенная прибыль (непокрытый убыток) до корректировок | B14: 3401 | C14: 0 | D14: 0 | E14: 0 | F14: 0
A15: корректировка в связи с:
A16: изменением учетной политики | B16: 3411 | C16: 0 | D16: 0 | E16: 0 | F16: 0
A17: исправлением ошибок | B17: 3421 | C17: 0 | D17: 0 | E17: 0 | F17: 0
A18: после корректировок | B18: 3501 | C18: 0 | D18: 0 | E18: 0 | F18: 0
A19: добавочный капитал до корректировок | B19: 3402 | C19: 0 | D19: 0 | E19: 0 | F19: 0
A20: корректировка в связи с:
A21: изменением учетной политики | B21: 3412 | C21: 0 | D21: 0 | E21: 0 | F21: 0
A22: исправлением ошибок | B22: 3422 | C22: 0 | D22: 0 | E22: 0 | F22: 0
A23: после корректировок | B23: 3502 | C23: 0 | D23: 0 | E23: 0 | F23: 0
A24: резервный капитал до корректировок | B24: 3403 | C24: 0 | D24: 0 | E24: 0 | F24: 0
A25: корректировка в связи с:
A26: изменением учетной политики | B26: 3413 | C26: 0 | D26: 0 | E26: 0 | F26: 0
A27: исправлением ошибок | B27: 3423 | C27: 0 | D27: 0 | E27: 0 | F27: 0
A28: после корректировок | B28: 3503 | C28: 0 | D28: 0 | E28: 0 | F28: 0
A29: собственные акции, выкупленные у акционеров, до корректировок | B29: 3404 | C29: 0 | D29: 0 | E29: 0 | F29: 0
A30: корректировка в связи с:
A31: изменением учетной политики | B31: 3414 | C31: 0 | D31: 0 | E31: 0 | F31: 0
A32: исправлением ошибок | B32: 3424 | C32: 0 | D32: 0 | E32: 0 | F32: 0
A33: после корректировок | B33: 3504 | C33: 0 | D33: 0 | E33: 0 | F33: 0
A34: фонд социальной сферы государственной до корректировок | B34: 3405 | C34: 0 | D34: 0 | E34: 0 | F34: 0
A35: корректировка в связи с:
A36: изменением учетной политики | B36: 3415 | C36: 0 | D36: 0 | E36: 0 | F36: 0
A37: исправлением ошибок | B37: 3425 | C37: 0 | D37: 0 | E37: 0 | F37: 0
A38: после корректировок | B38: 3505 | C38: 0 | D38: 0 | E38: 0 | F38: 0
D40: Форма 0710004 с.4
A41: 3. Чистые активы
A43: Наименование показателя | B43: Код строки | C43: ="На " & DAY('Общие сведения'!$D$2) & CHOOSE(MONTH('Общие сведения'!$D$2), " января ", " февраля ", " марта ", " апреля ", " мая ", " июня ", " июля ", " августа ", " сентября ", " октября ", " ноября ", " декабря ") & " " & YEAR('Общие сведения'!$D$2) & " г." -> На 31 марта 2026 г. | D43: ="На 31 декабря " & YEAR('Общие сведения'!$D$2)-1 & " г." -> На 31 декабря 2025 г. | E43: ="На 31 декабря " & YEAR('Общие сведения'!$D$2)-2 & " г." -> На 31 декабря 2024 г.
A44: 1 | C44: 3
A45: Чистые активы | B45: 3600 | C45: 0 | D45: 0 | E45: 0
A47: ='Общие сведения'!#REF! -> #REF! | D47: ='Общие сведения'!#REF! -> #REF!
A48: _______________________ | D48: ____________________
A49: (подпись) (расшифровка подписи) | D49: (подпись) (расшифровка подписи)
A50: "____" _________________ 2025 г.
A52: (НЕ ДЛЯ ПЕЧАТИ)
A53: Вычисляемые значения только для экспорта в XML-файл: | B53: 3402+3403+3404+3405 | C53: =C19+C24+C29+C34 -> 0 | D53: =D19+D24+D29+D34 -> 0 | E53: =E19+E24+E29+E34 -> 0 | F53: =F19+F24+F29+F34 -> 0
A54: корректировка в связи с:
A55: изменением учетной политики | B55: 3412+3413+3414+3415 | C55: =C21+C26+C31+C36 -> 0 | D55: =D21+D26+D31+D36 -> 0 | E55: =E21+E26+E31+E36 -> 0 | F55: =F21+F26+F31+F36 -> 0
A56: исправлением ошибок | B56: 3422+3423+3224+3425 | C56: =C22+C27+C32+C37 -> 0 | D56: =D22+D27+D32+D37 -> 0 | E56: =E22+E27+E32+E37 -> 0 | F56: =F22+F27+F32+F37 -> 0
A57: после корректировок | B57: 3502+3503+3504+3505 | C57: =C23+C28+C33+C38 -> 0 | D57: =D23+D28+D33+D38 -> 0 | E57: =E23+E28+E33+E38 -> 0 | F57: =F23+F28+F33+F38 -> 0

Sheet Движение денежных средств
A2: Отчет о движении денежных средств
A3: ="за " & IF(MONTH('Общие сведения'!D2)=3, "январь - март " & YEAR('Общие сведения'!D2) & " года", IF(MONTH('Общие сведения'!D2)=6, "январь - июнь " & YEAR('Общие сведения'!D2) & " года", IF(MONTH('Общие сведения'!D2)=9, "январь - сентябрь " & YEAR('Общие сведения'!D2) & " года", YEAR('Общие сведения'!D2) & " год"))) -> за январь - март 2026 года
E6: Коды
C7: Форма по ОКУД | E7: 0710005 | G7: форма 4
B8: Отчетная дата (число,месяц,год) | E8: =" " & 'Общие сведения'!D16 -> 31 / 03 / 2026
A9: =" Организация " & 'Общие сведения'!D18 -> Организация | D9: по ОКПО | E9: =" " & 'Общие сведения'!$D19
A13: Единица измерения: тыс.руб. | D13: по ОКЕИ | E13: =" " & 'Общие сведения'!D15 -> 384
A15: Пояс-нения | B15: Наименование показателя | C15: Код показателя | D15: ="За " & IF(MONTH('Общие сведения'!D2)=3, "январь-март " & YEAR('Общие сведения'!D2) & " г.", IF(MONTH('Общие сведения'!D2)=6, "январь-июнь " & YEAR('Общие сведения'!D2) & " г.", IF(MONTH('Общие сведения'!D2)=9, "январь-сентябрь " & YEAR('Общие сведения'!D2) & " г.", YEAR('Общие сведения'!D2) & " г."))) -> За январь-март 2026 г. | E15: ="За " & IF(MONTH('Общие сведения'!D2)=3, "январь-март " & YEAR('Общие сведения'!D2)-1 & " г.", IF(MONTH('Общие сведения'!D2)=6, "январь-июнь " & YEAR('Общие сведения'!D2)-1 & " г.", IF(MONTH('Общие сведения'!D2)=9, "январь-сентябрь " & YEAR('Общие сведения'!D2)-1 & " г.", YEAR('Общие сведения'!D2)-1 & " г."))) -> За январь-март 2025 г.
B16: Код АСКО | D16: D | E16: E
B17: Денежные потоки от текущих операций
B18: Поступления - всего, в том числе: | C18: 4110
B19: от продажи продукции, товаров, выполнения работ, оказания услуг | C19: 4111
B20: арендных платежей, роялти, комиссионных и иных аналогичных платежей | C20: 4112
B21: от перепродажи финансовых вложений | C21: 4113
B22: процентов по дебиторской задолженности покупателей | C22: 4114
B23: прочие поступления | C23: 4119
B27: Платежи - всего, в том числе: | C27: 4120
B28: поставщикам (подрядчикам) за сырье, материалы, выполненные работы, оказанные услуги | C28: 4121
B29: в связи с оплатой труда работников | C29: 4122
B30: процентов по долговым обязательствам | C30: 4123
B31: налога на прибыль организаций | C31: 4124
B32: прочие платежи | C32: 4129
B36: Сальдо денежных потоков от текущих операций | C36: 4100
D37: Форма 0710005 с.2
A38: Пояс-нения | B38: Наименование показателя | C38: Код показателя | D38: =D15 -> За январь-март 2026 г. | E38: =E15 -> За январь-март 2025 г.
B39: Денежные потоки от инвестиционных операций
B40: Поступления - всего, в том числе: | C40: 4210
B41: от продажи внеоборотных активов (кроме финансовых вложений) | C41: 4211
B42: от продажи акций других организаций (долей участия) | C42: 4212
B43: от возврата предоставленных займов, от продажи долговых ценных бумаг (прав требования денежных средств к другим лицам) | C43: 4213
B44: дивидендов, процентов по долговым финансовым вложениям и аналогичных поступлений от долевого участия в других организациях | C44: 4214
B46: прочие поступления | C46: 4219
B51: Платежи - всего, в том числе: | C51: 4220
B52: в связи с приобретением, созданием, модернизацией, реконструкцией и подготовкой к использованию внеоборотных активов | C52: 4221
B53: в связи с приобретением акций других организаций (долей участия) | C53: 4222
B54: в связи с приобретением долговых ценных бумаг (прав требования денежных средств к другим лицам), предоставление займов другим лицам | C54: 4223
B55: процентов по долговым обязательствам, включаемым в стоимость инвестиционного актива | C55: 4224
B57: прочие платежи | C57: 4229
B61: Сальдо денежных потоков от инвестиционных операций | C61: 4200
B62: Денежные потоки от финансовых операций
B63: Поступления - всего, в том числе: | C63: 4310
B64: получение кредитов и займов | C64: 4311
B65: денежных вкладов собственников (участников) | C65: 4312
B66: от выпуска акций, увеличения долей участия | C66: 4313
B67: от выпуска облигаций, векселей и других долговых ценных бумаг | C67: 4314
B68: от бессрочных облигаций и займов | C68: 4315
B69: прочие поступления | C69: 4319
D78: Форма 0710005 с.3
A79: Пояс-нения | B79: Наименование показателя | C79: Код показателя | D79: =D38 -> За январь-март 2026 г. | E79: =E38 -> За январь-март 2025 г.
B80: Платежи - всего, в том числе: | C80: 4320
B81: собственникам (участникам) в связи с выкупом у них акций (долей участия) организации или их выходом из состава участников | C81: 4321
B82: на уплату дивидендов и иных платежей по распределению прибыли в пользу собственников (участников) | C82: 4322
B83: в связи с погашением (выкупом) векселей и других долговых ценных бумаг, возврат кредитов и займов | C83: 4323
B84: связанные с бессрочными облигациями и займами | C84: 4324
B86: прочие платежи | C86: 4329
B87: Сальдо денежных потоков от финансовых операций | C87: 4300
B88: Сальдо денежных потоков за период | C88: 4400
B89: Остаток денежных средств и денежных эквивалентов на начало периода | C89: 4450
B90: Остаток денежных средств и денежных эквивалентов на конец периода | C90: 4500
B91: Величина влияния изменения курса иностранной валюты по отношению к рублю | C91: 4490
B93: ='Общие сведения'!B34 -> Наим. должности (Генеральный директор, Руководитель, ... )
B94: (наименование должности)
D97: ='Общие сведения'!D34 -> 0
B98: (подпись) | D98: (расшифровка подписи)
B100: "_____" ________________________ 2026 г.

Sheet 5.1.1
A11: ПОЯСНЕНИЯ К БУХГАЛТЕРСКОМУ БАЛАНСУ И ОТЧЕТУ О ФИНАНСОВЫХ РЕЗУЛЬТАТАХ
O12: с.1
A13: 1. Нематериальные активы
A15: 1.1 Наличие и движение нематериальных активов
A16: Единица измерения: тыс.руб.
A17: Наименование показателя | B17: Код АСКО | C17: Период | D17: На начало года | F17: Изменения за период | N17: На конец периода
D18: первоначальная (фактическая) стоимость | E18: накопленные амортизация и обесценение | F18: поступило | H18: выбыло | J18: начислено амортиза-ции | K18: обесцене-ние | L18: переклассификация, в т.ч. в долгосрочные активы к продаже | N18: первоначальная (фактическая) стоимость | O18: накопленные амортизация и обесценение
F19: первоначальная (фактическая) стоимость | G19: накопленные амортизация и обесценение | H19: первоначальная (фактическая) стоимость | I19: накопленные амортизация и обесценение | L19: первоначальная (фактическая) стоимость | M19: накопленные амортизация и обесценение
A20: Код АСКО | D20: D | E20: E | F20: F | G20: G | H20: H | I20: I | J20: J | K20: K | L20: L | M20: M | N20: N | O20: O | Q20: годовые
A21: Нематериальные активы - всего | B21: 10 | C21: ="за " & IF(MONTH('Общие сведения'!D2)=3, "январь-март " & YEAR('Общие сведения'!D2) & " г.", IF(MONTH('Общие сведения'!D2)=6, "январь-июнь " & YEAR('Общие сведения'!D2) & " г.", IF(MONTH('Общие сведения'!D2)=9, "январь-сентябрь " & YEAR('Общие сведения'!D2) & " г.", YEAR('Общие сведения'!D2) & " г."))) -> за январь-март 2026 г. | D21: =D24+D43+D45 -> 0 | E21: =E24+E43+E45 -> 0 | F21: =F24+F43+F45 -> 0 | G21: =G24+G43+G45 -> 0 | H21: =H24+H43+H45 -> 0 | I21: =I24+I43+I45 -> 0 | J21: =J24+J43+J45 -> 0 | K21: =K24+K43+K45 -> 0 | ... M21: =M24+M43+M45 -> 0 | N21: =D21+F21+H21+L21 -> 0 | O21: =E21+G21+I21+J21+K21+M21 -> 0
B22: 11 | C22: ="за " & IF(MONTH('Общие сведения'!$D$2)=3, "январь-март " & YEAR('Общие сведения'!$D$2)-1 & " г.", IF(MONTH('Общие сведения'!$D$2)=6, "январь-июнь " & YEAR('Общие сведения'!$D$2)-1 & " г.", IF(MONTH('Общие сведения'!$D$2)=9, "январь-сентябрь " & YEAR('Общие сведения'!$D$2)-1 & " г.", YEAR('Общие сведения'!$D$2)-1 & " г."))) -> за январь-март 2025 г. | D22: =D25+D44+D46 -> 0 | E22: =E25+E44+E46 -> 0 | F22: =F25+F44+F46 -> 0 | G22: =G25+G44+G46 -> 0 | H22: =H25+H44+H46 -> 0 | I22: =I25+I44+I46 -> 0 | J22: =J25+J44+J46 -> 0 | K22: =K25+K44+K46 -> 0 | ... M22: =M25+M44+M46 -> 0 | N22: =D22+F22+H22+L22 -> 0 | O22: =E22+G22+I22+J22+K22+M22 -> 0 | Q22: год
A23: в том числе:
A24: Права на объекты интеллектуальной собственности | B24: 20 | C24: ="за " & IF(MONTH('Общие сведения'!D2)=3, "январь-март " & YEAR('Общие сведения'!D2) & " г.", IF(MONTH('Общие сведения'!D2)=6, "январь-июнь " & YEAR('Общие сведения'!D2) & " г.", IF(MONTH('Общие сведения'!D2)=9, "январь-сентябрь " & YEAR('Общие сведения'!D2) & " г.", YEAR('Общие сведения'!D2) & " г."))) -> за январь-март 2026 г. | N24: =D24+F24+H24+L24 -> 0 | O24: =E24+G24+I24+J24+K24+M24 -> 0
B25: 21 | C25: ="за " & IF(MONTH('Общие сведения'!$D$2)=3, "январь-март " & YEAR('Общие сведения'!$D$2)-1 & " г.", IF(MONTH('Общие сведения'!$D$2)=6, "январь-июнь " & YEAR('Общие сведения'!$D$2)-1 & " г.", IF(MONTH('Общие сведения'!$D$2)=9, "январь-сентябрь " & YEAR('Общие сведения'!$D$2)-1 & " г.", YEAR('Общие сведения'!$D$2)-1 & " г."))) -> за январь-март 2025 г. | N25: =D25+F25+H25+L25 -> 0 | O25: =E25+G25+I25+J25+K25+M25 -> 0 | Q25: год
C26: резерв | N26: =D26+F26+H26+L26 -> 0 | O26: =E26+G26+I26+J26+K26+M26 -> 0 | Q26: резерв
C27: резерв | N27: =D27+F27+H27+L27 -> 0 | O27: =E27+G27+I27+J27+K27+M27 -> 0 | Q27: резерв
C28: резерв | N28: =D28+F28+H28+L28 -> 0 | O28: =E28+G28+I28+J28+K28+M28 -> 0 | Q28: резерв
C29: резерв | N29: =D29+F29+H29+L29 -> 0 | O29: =E29+G29+I29+J29+K29+M29 -> 0 | Q29: резерв
C30: резерв | N30: =D30+F30+H30+L30 -> 0 | O30: =E30+G30+I30+J30+K30+M30 -> 0 | Q30: резерв
C31: резерв | N31: =D31+F31+H31+L31 -> 0 | O31: =E31+G31+I31+J31+K31+M31 -> 0 | Q31: резерв
C32: резерв | N32: =D32+F32+H32+L32 -> 0 | O32: =E32+G32+I32+J32+K32+M32 -> 0 | Q32: резерв
C33: резерв | N33: =D33+F33+H33+L33 -> 0 | O33: =E33+G33+I33+J33+K33+M33 -> 0 | Q33: резерв
C34: резерв | N34: =D34+F34+H34+L34 -> 0 | O34: =E34+G34+I34+J34+K34+M34 -> 0 | Q34: резерв
C35: резерв | N35: =D35+F35+H35+L35 -> 0 | O35: =E35+G35+I35+J35+K35+M35 -> 0 | Q35: резерв
C36: резерв | N36: =D36+F36+H36+L36 -> 0 | O36: =E36+G36+I36+J36+K36+M36 -> 0 | Q36: резерв
C37: резерв | N37: =D37+F37+H37+L37 -> 0 | O37: =E37+G37+I37+J37+K37+M37 -> 0 | Q37: резерв
... C42: резерв | N42: =D42+F42+H42+L42 -> 0 | O42: =E42+G42+I42+J42+K42+M42 -> 0 | Q42: резерв
C43: резерв | Q43: резерв
C44: резерв | Q44: резерв
A45: Прочие | B45: 90 | C45: ="за " & IF(MONTH('Общие сведения'!D2)=3, "январь-март " & YEAR('Общие сведения'!D2) & " г.", IF(MONTH('Общие сведения'!D2)=6, "январь-июнь " & YEAR('Общие сведения'!D2) & " г.", IF(MONTH('Общие сведения'!D2)=9, "январь-сентябрь " & YEAR('Общие сведения'!D2) & " г.", YEAR('Общие сведения'!D2) & " г."))) -> за январь-март 2026 г. | N45: =D45+F45+H45+L45 -> 0 | O45: =E45+G45+I45+J45+K45+M45 -> 0
B46: 91 | C46: ="за " & IF(MONTH('Общие сведения'!$D$2)=3, "январь-март " & YEAR('Общие сведения'!$D$2)-1 & " г.", IF(MONTH('Общие сведения'!$D$2)=6, "январь-июнь " & YEAR('Общие сведения'!$D$2)-1 & " г.", IF(MONTH('Общие сведения'!$D$2)=9, "январь-сентябрь " & YEAR('Общие сведения'!$D$2)-1 & " г.", YEAR('Общие сведения'!$D$2)-1 & " г."))) -> за январь-март 2025 г. | N46: =D46+F46+H46+L46 -> 0 | O46: =E46+G46+I46+J46+K46+M46 -> 0 | Q46: год

Sheet 5.1.2
A1: Код АСКО | D1: D | E1: E | F1: F | G1: G | H1: H | I1: I | J1: J | K1: K | L1: L | M1: M | N1: N | O1: O | Q1: годовые
O2: с.2
A3: 1.2 Наличие и движение нематериальных активов, созданных организацией
A4: Единица измерения: тыс.руб.
A5: Наименование показателя | B5: Код АСКО | C5: Период | D5: На начало года | F5: Изменения за период | N5: На конец периода
D6: первоначальная (фактическая) стоимость | E6: накопленные амортизация и обесценение | F6: поступило | H6: выбыло | J6: начислено амортиза-ции | K6: обесцене-ние | L6: переклассификация, в т.ч. в долгосрочные активы к продаже | N6: первоначальная (фактическая) стоимость | O6: накопленные амортизация и обесценение
F7: первоначаль-ная (фактическая) стоимость | G7: накопленные амортизация и обесценение | H7: первоначаль-ная (фактическая) стоимость | I7: накопленные амортизация и обесценение | L7: первоначаль-ная (фактическая) стоимость | M7: накопленные амортизация и обесценение
A8: Нематериальные активы - всего | B8: 10 | C8: ="за " & IF(MONTH('Общие сведения'!D2)=3, "январь-март " & YEAR('Общие сведения'!D2) & " г.", IF(MONTH('Общие сведения'!D2)=6, "январь-июнь " & YEAR('Общие сведения'!D2) & " г.", IF(MONTH('Общие сведения'!D2)=9, "январь-сентябрь " & YEAR('Общие сведения'!D2) & " г.", YEAR('Общие сведения'!D2) & " г."))) -> за январь-март 2026 г. | D8: =D11+D30 -> 0 | E8: =E11+E30 -> 0 | F8: =F11+F30 -> 0 | G8: =G11+G30 -> 0 | H8: =H11+H30 -> 0 | I8: =I11+I30 -> 0 | J8: =J11+J30 -> 0 | K8: =K11+K30 -> 0 | ... M8: =M11+M30 -> 0 | N8: =D8+F8+H8+L8 -> 0 | O8: =E8+G8+I8+J8+K8+M8 -> 0
B9: 11 | C9: ="за " & IF(MONTH('Общие сведения'!D2)=3, "январь-март " & YEAR('Общие сведения'!D2)-1 & " г.", IF(MONTH('Общие сведения'!D2)=6, "январь-июнь " & YEAR('Общие сведения'!D2)-1 & " г.", IF(MONTH('Общие сведения'!D2)=9, "январь-сентябрь " & YEAR('Общие сведения'!D2)-1 & " г.", YEAR('Общие сведения'!D2)-1 & " г."))) -> за январь-март 2025 г. | D9: =D12+D31 -> 0 | E9: =E12+E31 -> 0 | F9: =F12+F31 -> 0 | G9: =G12+G31 -> 0 | H9: =H12+H31 -> 0 | I9: =I12+I31 -> 0 | J9: =J12+J31 -> 0 | K9: =K12+K31 -> 0 | ... M9: =M12+M31 -> 0 | N9: =D9+F9+H9+L9 -> 0 | O9: =E9+G9+I9+J9+K9+M9 -> 0 | Q9: год
A10: в том числе:
A11: Права на объекты интеллектуальной собственности | B11: 20 | C11: ="за " & IF(MONTH('Общие сведения'!D2)=3, "январь-март " & YEAR('Общие сведения'!D2) & " г.", IF(MONTH('Общие сведения'!D2)=6, "январь-июнь " & YEAR('Общие сведения'!D2) & " г.", IF(MONTH('Общие сведения'!D2)=9, "январь-сентябрь " & YEAR('Общие сведения'!D2) & " г.", YEAR('Общие сведения'!D2) & " г."))) -> за январь-март 2026 г. | N11: =D11+F11+H11+L11 -> 0 | O11: =E11+G11+I11+J11+K11+M11 -> 0
B12: 21 | C12: ="за " & IF(MONTH('Общие сведения'!D2)=3, "январь-март " & YEAR('Общие сведения'!D2)-1 & " г.", IF(MONTH('Общие сведения'!D2)=6, "январь-июнь " & YEAR('Общие сведения'!D2)-1 & " г.", IF(MONTH('Общие сведения'!D2)=9, "январь-сентябрь " & YEAR('Общие сведения'!D2)-1 & " г.", YEAR('Общие сведения'!D2)-1 & " г."))) -> за январь-март 2025 г. | N12: =D12+F12+H12+L12 -> 0 | O12: =E12+G12+I12+J12+K12+M12 -> 0 | Q12: год
C13: резерв | N13: =D13+F13+H13+L13 -> 0 | O13: =E13+G13+I13+J13+K13+M13 -> 0 | Q13: резерв
C14: резерв | N14: =D14+F14+H14+L14 -> 0 | O14: =E14+G14+I14+J14+K14+M14 -> 0 | Q14: резерв
C15: резерв | N15: =D15+F15+H15+L15 -> 0 | O15: =E15+G15+I15+J15+K15+M15 -> 0 | Q15: резерв
C16: резерв | N16: =D16+F16+H16+L16 -> 0 | O16: =E16+G16+I16+J16+K16+M16 -> 0 | Q16: резерв
C17: резерв | N17: =D17+F17+H17+L17 -> 0 | O17: =E17+G17+I17+J17+K17+M17 -> 0 | Q17: резерв
C18: резерв | N18: =D18+F18+H18+L18 -> 0 | O18: =E18+G18+I18+J18+K18+M18 -> 0 | Q18: резерв
C19: резерв | N19: =D19+F19+H19+L19 -> 0 | O19: =E19+G19+I19+J19+K19+M19 -> 0 | Q19: резерв
C20: резерв | N20: =D20+F20+H20+L20 -> 0 | O20: =E20+G20+I20+J20+K20+M20 -> 0 | Q20: резерв
C21: резерв | N21: =D21+F21+H21+L21 -> 0 | O21: =E21+G21+I21+J21+K21+M21 -> 0 | Q21: резерв
C22: резерв | N22: =D22+F22+H22+L22 -> 0 | O22: =E22+G22+I22+J22+K22+M22 -> 0 | Q22: резерв
C23: резерв | N23: =D23+F23+H23+L23 -> 0 | O23: =E23+G23+I23+J23+K23+M23 -> 0 | Q23: резерв
C24: резерв | N24: =D24+F24+H24+L24 -> 0 | O24: =E24+G24+I24+J24+K24+M24 -> 0 | Q24: резерв
... C29: резерв | N29: =D29+F29+H29+L29 -> 0 | O29: =E29+G29+I29+J29+K29+M29 -> 0 | Q29: резерв
A30: Прочие | B30: 90 | C30: ="за " & IF(MONTH('Общие сведения'!D2)=3, "январь-март " & YEAR('Общие сведения'!D2) & " г.", IF(MONTH('Общие сведения'!D2)=6, "январь-июнь " & YEAR('Общие сведения'!D2) & " г.", IF(MONTH('Общие сведения'!D2)=9, "январь-сентябрь " & YEAR('Общие сведения'!D2) & " г.", YEAR('Общие сведения'!D2) & " г."))) -> за январь-март 2026 г. | N30: =D30+F30+H30+L30 -> 0 | O30: =E30+G30+I30+J30+K30+M30 -> 0
B31: 91 | C31: ="за " & IF(MONTH('Общие сведения'!D2)=3, "январь-март " & YEAR('Общие сведения'!D2)-1 & " г.", IF(MONTH('Общие сведения'!D2)=6, "январь-июнь " & YEAR('Общие сведения'!D2)-1 & " г.", IF(MONTH('Общие сведения'!D2)=9, "январь-сентябрь " & YEAR('Общие сведения'!D2)-1 & " г.", YEAR('Общие сведения'!D2)-1 & " г."))) -> за январь-март 2025 г. | N31: =D31+F31+H31+L31 -> 0 | O31: =E31+G31+I31+J31+K31+M31 -> 0 | Q31: год

Sheet 5.1.3
G12: с.3 | I12: с.3
A13: 1.3 Капитальные вложения в объекты нематериальных активов
A14: Единица измерения: тыс.руб.
A15: Наименование показателя | C15: Код АСКО | D15: ="на " & DAY('Общие сведения'!$D$2) & CHOOSE(MONTH('Общие сведения'!$D$2), " января ", " февраля ", " марта ", " апреля ", " мая ", " июня ", " июля ", " августа ", " сентября ", " октября ", " ноября ", " декабря ") & " " & YEAR('Общие сведения'!$D$2) & " г." -> на 31 марта 2026 г. | F15: ="на 31 декабря " & YEAR('Общие сведения'!$D$2)-1 & " г." -> на 31 декабря 2025 г. | H15: ="на 31 декабря " & YEAR('Общие сведения'!$D$2)-2 & " г." -> на 31 декабря 2024 г.
D16: первоначальные (фактические) затраты | E16: накопленное обесценение | F16: первоначальные (фактические) затраты | G16: накопленное обесценение | H16: первоначальные (фактические) затраты | I16: накопленное обесценение
A17: Код АСКО | D17: D | E17: E | F17: F | G17: G | K17: годовые/резерв
A18: Незаконченные операции по приобретению и созданию нематериальных активов | C18: 10
A19: в том числе: | K19: резерв
K20: резерв

Sheet 5.2.1
F2: Коды
F3: 0710001
E4: Дата(число,месяц,год) .
A5: Организация | E5: по ОКПО .
A6: Идентификационный номер налогоплательщика | E6: ИНН .
A7: Вид экономической деятельности | E7: по ОКВЭД .
A8: Организационно-правовая форма / форма собственности
E9: по ОКОПФ/ОКФС .
A10: Единица измерения: тыс.руб. | E10: по ОКЕИ . | F10: 384
A11: Местонахождение (адрес)
O12: с.4
A13: 2. Основные средства
A15: 2.1 Наличие и движение основных средств
A16: Единица измерения: тыс.руб.
A17: Наименование показателя | B17: Код АСКО | C17: Период | D17: На начало года | F17: Изменения за период | N17: На конец периода
D18: первоначальная (фактическая) стоимость | E18: накопленные амортизация и обесценение | F18: поступило | H18: выбыло объектов | J18: начислено амортиза-ции | K18: обесцене-ние | L18: переклассификация, в т.ч. в долгосрочные активы к продаже | N18: первоначальная (фактическая) стоимость | O18: накопленные амортизация и обесценение
F19: первоначаль-ная (фактическая) стоимость | G19: накоплен-ные аморти-зация и обесценение | H19: первоначаль-ная (фактическая) стоимость | I19: накоплен-ные аморти-зация и обесценение | L19: первоначальная (фактическая) стоимость | M19: накопленные амортизация и обесценение
A20: Код АСКО | D20: D | E20: E | F20: F | G20: G | H20: H | I20: I | J20: J | K20: K | L20: L | M20: M | N20: N | O20: O | Q20: годовые
A21: Основные средства (без учета инвестиционной недвижимости) - всего | B21: 10 | C21: ="за " & IF(MONTH('Общие сведения'!D2)=3, "январь-март " & YEAR('Общие сведения'!D2) & " г.", IF(MONTH('Общие сведения'!D2)=6, "январь-июнь " & YEAR('Общие сведения'!D2) & " г.", IF(MONTH('Общие сведения'!D2)=9, "январь-сентябрь " & YEAR('Общие сведения'!D2) & " г.", YEAR('Общие сведения'!D2) & " г."))) -> за январь-март 2026 г. | D21: =D25+D27+D29+D31+D33 -> 0 | E21: =E25+E27+E29+E31+E33 -> 0 | F21: =F25+F27+F29+F31+F33 -> 0 | G21: =G25+G27+G29+G31+G33 -> 0 | H21: =H25+H27+H29+H31+H33 -> 0 | I21: =I25+I27+I29+I31+I33 -> 0 | J21: =J25+J27+J29+J31+J33 -> 0 | K21: =K25+K27+K29+K31+K33 -> 0 | ... O21: =O25+O27+O29+O31+O33 -> 0
B22: 11 | C22: ="за " & IF(MONTH('Общие сведения'!$D$2)=3, "январь-март " & YEAR('Общие сведения'!$D$2)-1 & " г.", IF(MONTH('Общие сведения'!$D$2)=6, "январь-июнь " & YEAR('Общие сведения'!$D$2)-1 & " г.", IF(MONTH('Общие сведения'!$D$2)=9, "январь-сентябрь " & YEAR('Общие сведения'!$D$2)-1 & " г.", YEAR('Общие сведения'!$D$2)-1 & " г."))) -> за январь-март 2025 г. | D22: =D26+D28+D30+D32+D34 -> 0 | E22: =E26+E28+E30+E32+E34 -> 0 | F22: =F26+F28+F30+F32+F34 -> 0 | G22: =G26+G28+G30+G32+G34 -> 0 | H22: =H26+H28+H30+H32+H34 -> 0 | I22: =I26+I28+I30+I32+I34 -> 0 | J22: =J26+J28+J30+J32+J34 -> 0 | K22: =K26+K28+K30+K32+K34 -> 0 | ... O22: =O26+O28+O30+O32+O34 -> 0 | Q22: год
A23: в том числе:
C24: резерв | F24: =D24-E24 -> 0 | Q24: резерв
A25: магистральные трубопроводы | B25: 20 | C25: ="за " & IF(MONTH('Общие сведения'!D2)=3, "январь-март " & YEAR('Общие сведения'!D2) & " г.", IF(MONTH('Общие сведения'!D2)=6, "январь-июнь " & YEAR('Общие сведения'!D2) & " г.", IF(MONTH('Общие сведения'!D2)=9, "январь-сентябрь " & YEAR('Общие сведения'!D2) & " г.", YEAR('Общие сведения'!D2) & " г."))) -> за январь-март 2026 г. | N25: =D25+F25+H25+L25 -> 0 | O25: =E25+G25+J25+I25+K25+M25 -> 0
B26: 21 | C26: ="за " & IF(MONTH('Общие сведения'!$D$2)=3, "январь-март " & YEAR('Общие сведения'!$D$2)-1 & " г.", IF(MONTH('Общие сведения'!$D$2)=6, "январь-июнь " & YEAR('Общие сведения'!$D$2)-1 & " г.", IF(MONTH('Общие сведения'!$D$2)=9, "январь-сентябрь " & YEAR('Общие сведения'!$D$2)-1 & " г.", YEAR('Общие сведения'!$D$2)-1 & " г."))) -> за январь-март 2025 г. | N26: =D26+F26+H26+L26 -> 0 | O26: =E26+G26+J26+I26+K26+M26 -> 0 | Q26: год
A27: скважины | B27: 30 | C27: ="за " & IF(MONTH('Общие сведения'!D2)=3, "январь-март " & YEAR('Общие сведения'!D2) & " г.", IF(MONTH('Общие сведения'!D2)=6, "январь-июнь " & YEAR('Общие сведения'!D2) & " г.", IF(MONTH('Общие сведения'!D2)=9, "январь-сентябрь " & YEAR('Общие сведения'!D2) & " г.", YEAR('Общие сведения'!D2) & " г."))) -> за январь-март 2026 г. | N27: =D27+F27+H27+L27 -> 0 | O27: =E27+G27+J27+I27+K27+M27 -> 0
B28: 31 | C28: ="за " & IF(MONTH('Общие сведения'!$D$2)=3, "январь-март " & YEAR('Общие сведения'!$D$2)-1 & " г.", IF(MONTH('Общие сведения'!$D$2)=6, "январь-июнь " & YEAR('Общие сведения'!$D$2)-1 & " г.", IF(MONTH('Общие сведения'!$D$2)=9, "январь-сентябрь " & YEAR('Общие сведения'!$D$2)-1 & " г.", YEAR('Общие сведения'!$D$2)-1 & " г."))) -> за январь-март 2025 г. | N28: =D28+F28+H28+L28 -> 0 | O28: =E28+G28+J28+I28+K28+M28 -> 0 | Q28: год
A29: машины и оборудование | B29: 40 | C29: ="за " & IF(MONTH('Общие сведения'!D2)=3, "январь-март " & YEAR('Общие сведения'!D2) & " г.", IF(MONTH('Общие сведения'!D2)=6, "январь-июнь " & YEAR('Общие сведения'!D2) & " г.", IF(MONTH('Общие сведения'!D2)=9, "январь-сентябрь " & YEAR('Общие сведения'!D2) & " г.", YEAR('Общие сведения'!D2) & " г."))) -> за январь-март 2026 г. | N29: =D29+F29+H29+L29 -> 0 | O29: =E29+G29+J29+I29+K29+M29 -> 0
B30: 41 | C30: ="за " & IF(MONTH('Общие сведения'!$D$2)=3, "январь-март " & YEAR('Общие сведения'!$D$2)-1 & " г.", IF(MONTH('Общие сведения'!$D$2)=6, "январь-июнь " & YEAR('Общие сведения'!$D$2)-1 & " г.", IF(MONTH('Общие сведения'!$D$2)=9, "январь-сентябрь " & YEAR('Общие сведения'!$D$2)-1 & " г.", YEAR('Общие сведения'!$D$2)-1 & " г."))) -> за январь-март 2025 г. | N30: =D30+F30+H30+L30 -> 0 | O30: =E30+G30+J30+I30+K30+M30 -> 0 | Q30: год
A31: здания, дороги, прочие сооружения произв. назначения | B31: 50 | C31: ="за " & IF(MONTH('Общие сведения'!D2)=3, "январь-март " & YEAR('Общие сведения'!D2) & " г.", IF(MONTH('Общие сведения'!D2)=6, "январь-июнь " & YEAR('Общие сведения'!D2) & " г.", IF(MONTH('Общие сведения'!D2)=9, "январь-сентябрь " & YEAR('Общие сведения'!D2) & " г.", YEAR('Общие сведения'!D2) & " г."))) -> за январь-март 2026 г. | N31: =D31+F31+H31+L31 -> 0 | O31: =E31+G31+J31+I31+K31+M31 -> 0
B32: 51 | C32: ="за " & IF(MONTH('Общие сведения'!$D$2)=3, "январь-март " & YEAR('Общие сведения'!$D$2)-1 & " г.", IF(MONTH('Общие сведения'!$D$2)=6, "январь-июнь " & YEAR('Общие сведения'!$D$2)-1 & " г.", IF(MONTH('Общие сведения'!$D$2)=9, "январь-сентябрь " & YEAR('Общие сведения'!$D$2)-1 & " г.", YEAR('Общие сведения'!$D$2)-1 & " г."))) -> за январь-март 2025 г. | N32: =D32+F32+H32+L32 -> 0 | O32: =E32+G32+J32+I32+K32+M32 -> 0 | Q32: год
A33: прочие ОС | B33: 60 | C33: ="за " & IF(MONTH('Общие сведения'!D2)=3, "январь-март " & YEAR('Общие сведения'!D2) & " г.", IF(MONTH('Общие сведения'!D2)=6, "январь-июнь " & YEAR('Общие сведения'!D2) & " г.", IF(MONTH('Общие сведения'!D2)=9, "январь-сентябрь " & YEAR('Общие сведения'!D2) & " г.", YEAR('Общие сведения'!D2) & " г."))) -> за январь-март 2026 г. | N33: =D33+F33+H33+L33 -> 0 | O33: =E33+G33+J33+I33+K33+M33 -> 0
B34: 61 | C34: ="за " & IF(MONTH('Общие сведения'!$D$2)=3, "январь-март " & YEAR('Общие сведения'!$D$2)-1 & " г.", IF(MONTH('Общие сведения'!$D$2)=6, "январь-июнь " & YEAR('Общие сведения'!$D$2)-1 & " г.", IF(MONTH('Общие сведения'!$D$2)=9, "январь-сентябрь " & YEAR('Общие сведения'!$D$2)-1 & " г.", YEAR('Общие сведения'!$D$2)-1 & " г."))) -> за январь-март 2025 г. | N34: =D34+F34+H34+L34 -> 0 | O34: =E34+G34+J34+I34+K34+M34 -> 0 | Q34: год
A35: Инвестиционная недвижимость - всего | B35: 70 | C35: ="за " & IF(MONTH('Общие сведения'!D2)=3, "январь-март " & YEAR('Общие сведения'!D2) & " г.", IF(MONTH('Общие сведения'!D2)=6, "январь-июнь " & YEAR('Общие сведения'!D2) & " г.", IF(MONTH('Общие сведения'!D2)=9, "январь-сентябрь " & YEAR('Общие сведения'!D2) & " г.", YEAR('Общие сведения'!D2) & " г."))) -> за январь-март 2026 г. | D35: =D39+D41+D43+D45+D47 -> 0 | E35: =E39+E41+E43+E45+E47 -> 0 | F35: =F39+F41+F43+F45+F47 -> 0 | G35: =G39+G41+G43+G45+G47 -> 0 | H35: =H39+H41+H43+H45+H47 -> 0 | I35: =I39+I41+I43+I45+I47 -> 0 | J35: =J39+J41+J43+J45+J47 -> 0 | K35: =K39+K41+K43+K45+K47 -> 0 | ... O35: =O39+O41+O43+O45+O47 -> 0
B36: 71 | C36: ="за " & IF(MONTH('Общие сведения'!$D$2)=3, "январь-март " & YEAR('Общие сведения'!$D$2)-1 & " г.", IF(MONTH('Общие сведения'!$D$2)=6, "январь-июнь " & YEAR('Общие сведения'!$D$2)-1 & " г.", IF(MONTH('Общие сведения'!$D$2)=9, "январь-сентябрь " & YEAR('Общие сведения'!$D$2)-1 & " г.", YEAR('Общие сведения'!$D$2)-1 & " г."))) -> за январь-март 2025 г. | D36: =D40+D42+D44+D46+D48 -> 0 | E36: =E40+E42+E44+E46+E48 -> 0 | F36: =F40+F42+F44+F46+F48 -> 0 | G36: =G40+G42+G44+G46+G48 -> 0 | H36: =H40+H42+H44+H46+H48 -> 0 | I36: =I40+I42+I44+I46+I48 -> 0 | J36: =J40+J42+J44+J46+J48 -> 0 | K36: =K40+K42+K44+K46+K48 -> 0 | ... O36: =O40+O42+O44+O46+O48 -> 0 | Q36: год
A37: в том числе:
C38: резерв | Q38: резерв
A39: магистральные трубопроводы | B39: 80 | C39: ="за " & IF(MONTH('Общие сведения'!D2)=3, "январь-март " & YEAR('Общие сведения'!D2) & " г.", IF(MONTH('Общие сведения'!D2)=6, "январь-июнь " & YEAR('Общие сведения'!D2) & " г.", IF(MONTH('Общие сведения'!D2)=9, "январь-сентябрь " & YEAR('Общие сведения'!D2) & " г.", YEAR('Общие сведения'!D2) & " г."))) -> за январь-март 2026 г. | N39: =D39+F39+H39+L39 -> 0 | O39: =E39+G39+J39+I39+K39+M39 -> 0
B40: 81 | C40: ="за " & IF(MONTH('Общие сведения'!$D$2)=3, "январь-март " & YEAR('Общие сведения'!$D$2)-1 & " г.", IF(MONTH('Общие сведения'!$D$2)=6, "январь-июнь " & YEAR('Общие сведения'!$D$2)-1 & " г.", IF(MONTH('Общие сведения'!$D$2)=9, "январь-сентябрь " & YEAR('Общие сведения'!$D$2)-1 & " г.", YEAR('Общие сведения'!$D$2)-1 & " г."))) -> за январь-март 2025 г. | N40: =D40+F40+H40+L40 -> 0 | O40: =E40+G40+J40+I40+K40+M40 -> 0 | Q40: год
A41: скважины | B41: 90 | C41: ="за " & IF(MONTH('Общие сведения'!D2)=3, "январь-март " & YEAR('Общие сведения'!D2) & " г.", IF(MONTH('Общие сведения'!D2)=6, "январь-июнь " & YEAR('Общие сведения'!D2) & " г.", IF(MONTH('Общие сведения'!D2)=9, "январь-сентябрь " & YEAR('Общие сведения'!D2) & " г.", YEAR('Общие сведения'!D2) & " г."))) -> за январь-март 2026 г. | N41: =D41+F41+H41+L41 -> 0 | O41: =E41+G41+J41+I41+K41+M41 -> 0
B42: 91 | C42: ="за " & IF(MONTH('Общие сведения'!$D$2)=3, "январь-март " & YEAR('Общие сведения'!$D$2)-1 & " г.", IF(MONTH('Общие сведения'!$D$2)=6, "январь-июнь " & YEAR('Общие сведения'!$D$2)-1 & " г.", IF(MONTH('Общие сведения'!$D$2)=9, "январь-сентябрь " & YEAR('Общие сведения'!$D$2)-1 & " г.", YEAR('Общие сведения'!$D$2)-1 & " г."))) -> за январь-март 2025 г. | N42: =D42+F42+H42+L42 -> 0 | O42: =E42+G42+J42+I42+K42+M42 -> 0 | Q42: год
C43: резерв | N43: =D43+F43+H43+L43 -> 0 | O43: =E43+G43+J43+I43+K43+M43 -> 0 | Q43: резерв
C44: резерв | N44: =D44+F44+H44+L44 -> 0 | O44: =E44+G44+J44+I44+K44+M44 -> 0 | Q44: резерв
A45: здания, дороги, прочие сооружения произв. назначения | B45: 100 | C45: ="за " & IF(MONTH('Общие сведения'!D2)=3, "январь-март " & YEAR('Общие сведения'!D2) & " г.", IF(MONTH('Общие сведения'!D2)=6, "январь-июнь " & YEAR('Общие сведения'!D2) & " г.", IF(MONTH('Общие сведения'!D2)=9, "январь-сентябрь " & YEAR('Общие сведения'!D2) & " г.", YEAR('Общие сведения'!D2) & " г."))) -> за январь-март 2026 г. | N45: =D45+F45+H45+L45 -> 0 | O45: =E45+G45+J45+I45+K45+M45 -> 0
B46: 101 | C46: ="за " & IF(MONTH('Общие сведения'!$D$2)=3, "январь-март " & YEAR('Общие сведения'!$D$2)-1 & " г.", IF(MONTH('Общие сведения'!$D$2)=6, "январь-июнь " & YEAR('Общие сведения'!$D$2)-1 & " г.", IF(MONTH('Общие сведения'!$D$2)=9, "январь-сентябрь " & YEAR('Общие сведения'!$D$2)-1 & " г.", YEAR('Общие сведения'!$D$2)-1 & " г."))) -> за январь-март 2025 г. | N46: =D46+F46+H46+L46 -> 0 | O46: =E46+G46+J46+I46+K46+M46 -> 0 | Q46: год
A47: прочие ОС | B47: 110 | C47: ="за " & IF(MONTH('Общие сведения'!D2)=3, "январь-март " & YEAR('Общие сведения'!D2) & " г.", IF(MONTH('Общие сведения'!D2)=6, "январь-июнь " & YEAR('Общие сведения'!D2) & " г.", IF(MONTH('Общие сведения'!D2)=9, "январь-сентябрь " & YEAR('Общие сведения'!D2) & " г.", YEAR('Общие сведения'!D2) & " г."))) -> за январь-март 2026 г. | N47: =D47+F47+H47+L47 -> 0 | O47: =E47+G47+J47+I47+K47+M47 -> 0
B48: 111 | C48: ="за " & IF(MONTH('Общие сведения'!$D$2)=3, "январь-март " & YEAR('Общие сведения'!$D$2)-1 & " г.", IF(MONTH('Общие сведения'!$D$2)=6, "январь-июнь " & YEAR('Общие сведения'!$D$2)-1 & " г.", IF(MONTH('Общие сведения'!$D$2)=9, "январь-сентябрь " & YEAR('Общие сведения'!$D$2)-1 & " г.", YEAR('Общие сведения'!$D$2)-1 & " г."))) -> за январь-март 2025 г. | N48: =D48+F48+H48+L48 -> 0 | O48: =E48+G48+J48+I48+K48+M48 -> 0 | Q48: год

Sheet 5.2.2
F2: Коды
F3: 0710001
E4: Дата(число,месяц,год) .
A5: Организация | E5: по ОКПО .
A6: Идентификационный номер налогоплательщика | E6: ИНН .
A7: Вид экономической деятельности | E7: по ОКВЭД .
A8: Организационно-правовая форма / форма собственности
E9: по ОКОПФ/ОКФС .
A10: Единица измерения: тыс.руб. | E10: по ОКЕИ . | F10: 384
A11: Местонахождение (адрес)
Q12: с.5
A14: 2.2 Наличие и движение прав пользования активами
A15: Единица измерения: тыс.руб.
A16: Наименование показателя | B16: Код АСКО | C16: Период | D16: На начало года | G16: Изменения за период | P16: На конец периода
D17: первоначаль-ная (фактическая) стоимость | E17: накопленные амортизация и обесценение | G17: поступило, в т.ч. в результате заключения новых договоров аренды | H17: выбыло объектов | J17: начислено амортизации | K17: обесценение | L17: эффект модификации и изменения оценок по договорам аренды | N17: переклассификация | P17: первоначаль-ная (фактическая) стоимость | Q17: накопленные амортизация и обесценение
H18: первоначаль-ная (фактическая) стоимость | I18: накопленные амортизация и обесценение | L18: первоначаль-ная (фактическая) стоимость | M18: накопленные амортизация и обесценение | N18: первоначаль-ная (фактическая) стоимость | O18: накопленные амортизация и обесценение
A19: Код АСКО | D19: D | E19: E | F19: F | G19: G | H19: H | I19: I | J19: J | K19: K | L19: L | M19: M | N19: N | O19: O | P19: P | Q19: Q | S19: годовые
A20: Права пользования активами - всего | B20: 10 | C20: ="за " & IF(MONTH('Общие сведения'!D2)=3, "январь-март " & YEAR('Общие сведения'!D2) & " г.", IF(MONTH('Общие сведения'!D2)=6, "январь-июнь " & YEAR('Общие сведения'!D2) & " г.", IF(MONTH('Общие сведения'!D2)=9, "январь-сентябрь " & YEAR('Общие сведения'!D2) & " г.", YEAR('Общие сведения'!D2) & " г."))) -> за январь-март 2026 г. | D20: =D24+D26+D28+D30+D32 -> 0 | E20: =E24+E26+E28+E30+E32 -> 0 | G20: =G24+G26+G28+G30+G32 -> 0 | H20: =H24+H26+H28+H30+H32 -> 0 | I20: =I24+I26+I28+I30+I32 -> 0 | J20: =J24+J26+J28+J30+J32 -> 0 | K20: =K24+K26+K28+K30+K32 -> 0 | L20: =L24+L26+L28+L30+L32 -> 0 | M20: =M24+M26+M28+M30+M32 -> 0 | N20: =N24+N26+N28+N30+N32 -> 0 | ... Q20: =Q24+Q26+Q28+Q30+Q32 -> 0
B21: 11 | C21: ="за " & IF(MONTH('Общие сведения'!$D$2)=3, "январь-март " & YEAR('Общие сведения'!$D$2)-1 & " г.", IF(MONTH('Общие сведения'!$D$2)=6, "январь-июнь " & YEAR('Общие сведения'!$D$2)-1 & " г.", IF(MONTH('Общие сведения'!$D$2)=9, "январь-сентябрь " & YEAR('Общие сведения'!$D$2)-1 & " г.", YEAR('Общие сведения'!$D$2)-1 & " г."))) -> за январь-март 2025 г. | D21: =D25+D27+D29+D31+D33 -> 0 | E21: =E25+E27+E29+E31+E33 -> 0 | G21: =G25+G27+G29+G31+G33 -> 0 | H21: =H25+H27+H29+H31+H33 -> 0 | I21: =I25+I27+I29+I31+I33 -> 0 | J21: =J25+J27+J29+J31+J33 -> 0 | K21: =K25+K27+K29+K31+K33 -> 0 | L21: =L25+L27+L29+L31+L33 -> 0 | M21: =M25+M27+M29+M31+M33 -> 0 | N21: =N25+N27+N29+N31+N33 -> 0 | ... Q21: =Q25+Q27+Q29+Q31+Q33 -> 0 | S21: год
A22: в том числе:
S23: резерв
A24: магистральные трубопроводы | B24: 20 | C24: ="за " & IF(MONTH('Общие сведения'!D2)=3, "январь-март " & YEAR('Общие сведения'!D2) & " г.", IF(MONTH('Общие сведения'!D2)=6, "январь-июнь " & YEAR('Общие сведения'!D2) & " г.", IF(MONTH('Общие сведения'!D2)=9, "январь-сентябрь " & YEAR('Общие сведения'!D2) & " г.", YEAR('Общие сведения'!D2) & " г."))) -> за январь-март 2026 г. | P24: =D24+G24+H24+L24+N24 -> 0 | Q24: =E24+I24+K24+J24+M24+O24 -> 0
B25: 21 | C25: ="за " & IF(MONTH('Общие сведения'!$D$2)=3, "январь-март " & YEAR('Общие сведения'!$D$2)-1 & " г.", IF(MONTH('Общие сведения'!$D$2)=6, "январь-июнь " & YEAR('Общие сведения'!$D$2)-1 & " г.", IF(MONTH('Общие сведения'!$D$2)=9, "январь-сентябрь " & YEAR('Общие сведения'!$D$2)-1 & " г.", YEAR('Общие сведения'!$D$2)-1 & " г."))) -> за январь-март 2025 г. | P25: =D25+G25+H25+L25+N25 -> 0 | Q25: =E25+I25+K25+J25+M25+O25 -> 0 | S25: год
A26: скважины | B26: 30 | C26: ="за " & IF(MONTH('Общие сведения'!D2)=3, "январь-март " & YEAR('Общие сведения'!D2) & " г.", IF(MONTH('Общие сведения'!D2)=6, "январь-июнь " & YEAR('Общие сведения'!D2) & " г.", IF(MONTH('Общие сведения'!D2)=9, "январь-сентябрь " & YEAR('Общие сведения'!D2) & " г.", YEAR('Общие сведения'!D2) & " г."))) -> за январь-март 2026 г. | P26: =D26+G26+H26+L26+N26 -> 0 | Q26: =E26+I26+K26+J26+M26+O26 -> 0
B27: 31 | C27: ="за " & IF(MONTH('Общие сведения'!$D$2)=3, "январь-март " & YEAR('Общие сведения'!$D$2)-1 & " г.", IF(MONTH('Общие сведения'!$D$2)=6, "январь-июнь " & YEAR('Общие сведения'!$D$2)-1 & " г.", IF(MONTH('Общие сведения'!$D$2)=9, "январь-сентябрь " & YEAR('Общие сведения'!$D$2)-1 & " г.", YEAR('Общие сведения'!$D$2)-1 & " г."))) -> за январь-март 2025 г. | P27: =D27+G27+H27+L27+N27 -> 0 | Q27: =E27+I27+K27+J27+M27+O27 -> 0 | S27: год
A28: машины и оборудование | B28: 40 | C28: ="за " & IF(MONTH('Общие сведения'!D2)=3, "январь-март " & YEAR('Общие сведения'!D2) & " г.", IF(MONTH('Общие сведения'!D2)=6, "январь-июнь " & YEAR('Общие сведения'!D2) & " г.", IF(MONTH('Общие сведения'!D2)=9, "январь-сентябрь " & YEAR('Общие сведения'!D2) & " г.", YEAR('Общие сведения'!D2) & " г."))) -> за январь-март 2026 г. | P28: =D28+G28+H28+L28+N28 -> 0 | Q28: =E28+I28+K28+J28+M28+O28 -> 0
B29: 41 | C29: ="за " & IF(MONTH('Общие сведения'!$D$2)=3, "январь-март " & YEAR('Общие сведения'!$D$2)-1 & " г.", IF(MONTH('Общие сведения'!$D$2)=6, "январь-июнь " & YEAR('Общие сведения'!$D$2)-1 & " г.", IF(MONTH('Общие сведения'!$D$2)=9, "январь-сентябрь " & YEAR('Общие сведения'!$D$2)-1 & " г.", YEAR('Общие сведения'!$D$2)-1 & " г."))) -> за январь-март 2025 г. | P29: =D29+G29+H29+L29+N29 -> 0 | Q29: =E29+I29+K29+J29+M29+O29 -> 0 | S29: год
A30: здания, дороги, прочие сооружения произв. назначения | B30: 50 | C30: ="за " & IF(MONTH('Общие сведения'!D2)=3, "январь-март " & YEAR('Общие сведения'!D2) & " г.", IF(MONTH('Общие сведения'!D2)=6, "январь-июнь " & YEAR('Общие сведения'!D2) & " г.", IF(MONTH('Общие сведения'!D2)=9, "январь-сентябрь " & YEAR('Общие сведения'!D2) & " г.", YEAR('Общие сведения'!D2) & " г."))) -> за январь-март 2026 г. | P30: =D30+G30+H30+L30+N30 -> 0 | Q30: =E30+I30+K30+J30+M30+O30 -> 0
B31: 51 | C31: ="за " & IF(MONTH('Общие сведения'!$D$2)=3, "январь-март " & YEAR('Общие сведения'!$D$2)-1 & " г.", IF(MONTH('Общие сведения'!$D$2)=6, "январь-июнь " & YEAR('Общие сведения'!$D$2)-1 & " г.", IF(MONTH('Общие сведения'!$D$2)=9, "январь-сентябрь " & YEAR('Общие сведения'!$D$2)-1 & " г.", YEAR('Общие сведения'!$D$2)-1 & " г."))) -> за январь-март 2025 г. | P31: =D31+G31+H31+L31+N31 -> 0 | Q31: =E31+I31+K31+J31+M31+O31 -> 0 | S31: год
A32: прочие ОС | B32: 60 | C32: ="за " & IF(MONTH('Общие сведения'!D2)=3, "январь-март " & YEAR('Общие сведения'!D2) & " г.", IF(MONTH('Общие сведения'!D2)=6, "январь-июнь " & YEAR('Общие сведения'!D2) & " г.", IF(MONTH('Общие сведения'!D2)=9, "январь-сентябрь " & YEAR('Общие сведения'!D2) & " г.", YEAR('Общие сведения'!D2) & " г."))) -> за январь-март 2026 г. | P32: =D32+G32+H32+L32+N32 -> 0 | Q32: =E32+I32+K32+J32+M32+O32 -> 0
B33: 61 | C33: ="за " & IF(MONTH('Общие сведения'!$D$2)=3, "январь-март " & YEAR('Общие сведения'!$D$2)-1 & " г.", IF(MONTH('Общие сведения'!$D$2)=6, "январь-июнь " & YEAR('Общие сведения'!$D$2)-1 & " г.", IF(MONTH('Общие сведения'!$D$2)=9, "январь-сентябрь " & YEAR('Общие сведения'!$D$2)-1 & " г.", YEAR('Общие сведения'!$D$2)-1 & " г."))) -> за январь-март 2025 г. | P33: =D33+G33+H33+L33+N33 -> 0 | Q33: =E33+I33+K33+J33+M33+O33 -> 0 | S33: год

Sheet 5.2.3
F2: Коды
F3: 0710001
E4: Дата(число,месяц,год) .
A5: Организация | E5: по ОКПО .
A6: Идентификационный номер налогоплательщика | E6: ИНН .
A7: Вид экономической деятельности | E7: по ОКВЭД .
A8: Организационно-правовая форма / форма собственности
E9: по ОКОПФ/ОКФС .
A10: Единица измерения: тыс.руб. | E10: по ОКЕИ . | F10: 384
A11: Местонахождение (адрес)
G12: с.6 | I12: с.6
A13: 2.3 Капитальные вложения в объекты основных средств, инвестиционной недвижимости и права пользования активами
A14: Единица измерения: тыс.руб.
A15: Наименование показателя | C15: Код АСКО | D15: ="на " & DAY('Общие сведения'!$D$2) & CHOOSE(MONTH('Общие сведения'!$D$2), " января ", " февраля ", " марта ", " апреля ", " мая ", " июня ", " июля ", " августа ", " сентября ", " октября ", " ноября ", " декабря ") & " " & YEAR('Общие сведения'!$D$2) & " г." -> на 31 марта 2026 г. | F15: ="на 31 декабря " & YEAR('Общие сведения'!$D$2)-1 & " г." -> на 31 декабря 2025 г. | H15: ="на 31 декабря " & YEAR('Общие сведения'!$D$2)-2 & " г." -> на 31 декабря 2024 г.
D16: первоначаль-ные (фактические) затраты | E16: накопленное обесценение | F16: первоначаль-ные (фактические) затраты | G16: накопленное обесценение | H16: первоначаль-ные (фактические) затраты | I16: накопленное обесценение
A17: Код АСКО | D17: D | E17: E | F17: F | G17: G | K17: годовые/резерв
A18: Капитальные вложения в объекты основных средств - всего | C18: 5 | D18: =D20+D21 -> 0 | E18: =E20+E21 -> 0 | F18: =F20+F21 -> 0 | G18: =G20+G21 -> 0 | H18: =H20+H21 -> 0 | I18: =I20+I21 -> 0
A19: в том числе:
A20: незавершенное строительство | C20: 10
A21: оборудование к установке | C21: 20
A22: Капитальные вложения в объекты инвестиционной недвижимости | C22: 30
A23: Капитальные вложения в права пользования активами | C23: 40

Sheet 5.2.4
F2: Коды
F3: 0710001
E4: Дата(число,месяц,год) .
A5: Организация | E5: по ОКПО .
A6: Идентификационный номер налогоплательщика | E6: ИНН .
A7: Вид экономической деятельности | E7: по ОКВЭД .
A8: Организационно-правовая форма / форма собственности
E9: по ОКОПФ/ОКФС .
A10: Единица измерения: тыс.руб. | E10: по ОКЕИ . | F10: 384
A11: Местонахождение (адрес)
G12: с.7 | I12: с.7
A13: 2.4 Основные средства, в отношении которых имеются ограничения использования
A14: Единица измерения: тыс.руб.
A15: Наименование показателя | C15: Код АСКО | D15: ="на " & DAY('Общие сведения'!$D$2) & CHOOSE(MONTH('Общие сведения'!$D$2), " января ", " февраля ", " марта ", " апреля ", " мая ", " июня ", " июля ", " августа ", " сентября ", " октября ", " ноября ", " декабря ") & " " & YEAR('Общие сведения'!$D$2) & " г." -> на 31 марта 2026 г. | F15: ="на 31 декабря " & YEAR('Общие сведения'!$D$2)-1 & " г." -> на 31 декабря 2025 г. | H15: ="на 31 декабря " & YEAR('Общие сведения'!$D$2)-2 & " г." -> на 31 декабря 2024 г.
A16: Код АСКО | D16: D | E16: E | F16: F | G16: G | K16: годовые/резерв
A17: Основные средства, предоставленные за плату во временное пользование | C17: 10
K18: резерв
A19: Пригодные для использования, но не используемые объекты основных средств | C19: 20
A20: Основные средства, в отношении которых имеются ограничения имущественных прав, в том числе находящиеся в залоге | C20: 30

Sheet 5.3.1
F3: Коды
F4: 0710001
E5: Дата(число,месяц,год) .
A6: Организация | E6: по ОКПО .
A7: Идентификационный номер налогоплательщика | E7: ИНН .
A8: Вид экономической деятельности | E8: по ОКВЭД .
A9: Организационно-правовая форма / форма собственности
E10: по ОКОПФ/ОКФС .
A11: Единица измерения: тыс.руб. | E11: по ОКЕИ . | F11: 384
A12: Местонахождение (адрес)
N13: с.8
A14: 3. Финансовые вложения
A16: 3.1 Наличие и движение финансовых вложений
A17: Единица измерения: тыс.руб.
A18: Наименование показателя | B18: Код АСКО | C18: Период | D18: На начало года | F18: Изменения за период | M18: На конец периода
D19: первоначальная стоимость | E19: накопленная корректи-ровка | F19: поступило | G19: выбыло (погашено) | I19: доведение первоначальной стоимости до номинальной | J19: текущей рыночной стоимости (убытков от обесценения) | K19: переклассификация | M19: первоначальная стоимость | N19: накопленная корректировка
G20: первоначальная стоимость | H20: накоплен-ная корректи-ровка | K20: первоначальная стоимость | L20: накоплен-ная корректи-ровка
A21: Код АСКО | D21: D | E21: E | F21: F | G21: G | H21: H | I21: I | J21: J | K21: K | L21: L | M21: M | N21: N | P21: годовые
A22: Долгосрочные финансовые вложения - всего | B22: 10 | C22: ="за " & IF(MONTH('Общие сведения'!D2)=3, "январь-март " & YEAR('Общие сведения'!D2) & " г.", IF(MONTH('Общие сведения'!D2)=6, "январь-июнь " & YEAR('Общие сведения'!D2) & " г.", IF(MONTH('Общие сведения'!D2)=9, "январь-сентябрь " & YEAR('Общие сведения'!D2) & " г.", YEAR('Общие сведения'!D2) & " г."))) -> за январь-март 2026 г. | D22: =D25+D27+D29+D31+D33 -> 0 | E22: =E25+E27+E29+E31+E33 -> 0 | F22: =F25+F27+F29+F31+F33 -> 0 | G22: =G25+G27+G29+G31+G33 -> 0 | H22: =H25+H27+H29+H31+H33 -> 0 | I22: =I25+I27+I29+I31+I33 -> 0 | J22: =J25+J27+J29+J31+J33 -> 0 | K22: =K25+K27+K29+K31+K33 -> 0 | ... N22: =N25+N27+N29+N31+N33 -> 0
B23: 11 | C23: ="за " & IF(MONTH('Общие сведения'!$D$2)=3, "январь-март " & YEAR('Общие сведения'!$D$2)-1 & " г.", IF(MONTH('Общие сведения'!$D$2)=6, "январь-июнь " & YEAR('Общие сведения'!$D$2)-1 & " г.", IF(MONTH('Общие сведения'!$D$2)=9, "январь-сентябрь " & YEAR('Общие сведения'!$D$2)-1 & " г.", YEAR('Общие сведения'!$D$2)-1 & " г."))) -> за январь-март 2025 г. | D23: =D26+D28+D30+D32+D34 -> 0 | E23: =E26+E28+E30+E32+E34 -> 0 | F23: =F26+F28+F30+F32+F34 -> 0 | G23: =G26+G28+G30+G32+G34 -> 0 | H23: =H26+H28+H30+H32+H34 -> 0 | I23: =I26+I28+I30+I32+I34 -> 0 | J23: =J26+J28+J30+J32+J34 -> 0 | K23: =K26+K28+K30+K32+K34 -> 0 | ... N23: =N26+N28+N30+N32+N34 -> 0 | P23: год
A24: в том числе:
A25: инвестиции в дочерние общества | B25: 20 | C25: ="за " & IF(MONTH('Общие сведения'!D2)=3, "январь-март " & YEAR('Общие сведения'!D2) & " г.", IF(MONTH('Общие сведения'!D2)=6, "январь-июнь " & YEAR('Общие сведения'!D2) & " г.", IF(MONTH('Общие сведения'!D2)=9, "январь-сентябрь " & YEAR('Общие сведения'!D2) & " г.", YEAR('Общие сведения'!D2) & " г."))) -> за январь-март 2026 г. | I25: 0 | M25: =D25+F25+G25+I25+K25 -> 0 | N25: =E25+H25+J25+L25 -> 0
B26: 21 | C26: ="за " & IF(MONTH('Общие сведения'!$D$2)=3, "январь-март " & YEAR('Общие сведения'!$D$2)-1 & " г.", IF(MONTH('Общие сведения'!$D$2)=6, "январь-июнь " & YEAR('Общие сведения'!$D$2)-1 & " г.", IF(MONTH('Общие сведения'!$D$2)=9, "январь-сентябрь " & YEAR('Общие сведения'!$D$2)-1 & " г.", YEAR('Общие сведения'!$D$2)-1 & " г."))) -> за январь-март 2025 г. | I26: 0 | M26: =D26+F26+G26+I26+K26 -> 0 | N26: =E26+H26+J26+L26 -> 0 | P26: год
A27: инвестиции в зависимые общества | B27: 30 | C27: ="за " & IF(MONTH('Общие сведения'!D2)=3, "январь-март " & YEAR('Общие сведения'!D2) & " г.", IF(MONTH('Общие сведения'!D2)=6, "январь-июнь " & YEAR('Общие сведения'!D2) & " г.", IF(MONTH('Общие сведения'!D2)=9, "январь-сентябрь " & YEAR('Общие сведения'!D2) & " г.", YEAR('Общие сведения'!D2) & " г."))) -> за январь-март 2026 г. | I27: 0 | M27: =D27+F27+G27+I27+K27 -> 0 | N27: =E27+H27+J27+L27 -> 0
B28: 31 | C28: ="за " & IF(MONTH('Общие сведения'!$D$2)=3, "январь-март " & YEAR('Общие сведения'!$D$2)-1 & " г.", IF(MONTH('Общие сведения'!$D$2)=6, "январь-июнь " & YEAR('Общие сведения'!$D$2)-1 & " г.", IF(MONTH('Общие сведения'!$D$2)=9, "январь-сентябрь " & YEAR('Общие сведения'!$D$2)-1 & " г.", YEAR('Общие сведения'!$D$2)-1 & " г."))) -> за январь-март 2025 г. | I28: 0 | M28: =D28+F28+G28+I28+K28 -> 0 | N28: =E28+H28+J28+L28 -> 0 | P28: год
A29: инвестиции в другие организации | B29: 40 | C29: ="за " & IF(MONTH('Общие сведения'!D2)=3, "январь-март " & YEAR('Общие сведения'!D2) & " г.", IF(MONTH('Общие сведения'!D2)=6, "январь-июнь " & YEAR('Общие сведения'!D2) & " г.", IF(MONTH('Общие сведения'!D2)=9, "январь-сентябрь " & YEAR('Общие сведения'!D2) & " г.", YEAR('Общие сведения'!D2) & " г."))) -> за январь-март 2026 г. | I29: 0 | M29: =D29+F29+G29+I29+K29 -> 0 | N29: =E29+H29+J29+L29 -> 0
B30: 41 | C30: ="за " & IF(MONTH('Общие сведения'!$D$2)=3, "январь-март " & YEAR('Общие сведения'!$D$2)-1 & " г.", IF(MONTH('Общие сведения'!$D$2)=6, "январь-июнь " & YEAR('Общие сведения'!$D$2)-1 & " г.", IF(MONTH('Общие сведения'!$D$2)=9, "январь-сентябрь " & YEAR('Общие сведения'!$D$2)-1 & " г.", YEAR('Общие сведения'!$D$2)-1 & " г."))) -> за январь-март 2025 г. | I30: 0 | M30: =D30+F30+G30+I30+K30 -> 0 | N30: =E30+H30+J30+L30 -> 0 | P30: год
A31: займы выданные | B31: 50 | C31: ="за " & IF(MONTH('Общие сведения'!D2)=3, "январь-март " & YEAR('Общие сведения'!D2) & " г.", IF(MONTH('Общие сведения'!D2)=6, "январь-июнь " & YEAR('Общие сведения'!D2) & " г.", IF(MONTH('Общие сведения'!D2)=9, "январь-сентябрь " & YEAR('Общие сведения'!D2) & " г.", YEAR('Общие сведения'!D2) & " г."))) -> за январь-март 2026 г. | M31: =D31+F31+G31+I31+K31 -> 0 | N31: =E31+H31+J31+L31 -> 0
B32: 51 | C32: ="за " & IF(MONTH('Общие сведения'!$D$2)=3, "январь-март " & YEAR('Общие сведения'!$D$2)-1 & " г.", IF(MONTH('Общие сведения'!$D$2)=6, "январь-июнь " & YEAR('Общие сведения'!$D$2)-1 & " г.", IF(MONTH('Общие сведения'!$D$2)=9, "январь-сентябрь " & YEAR('Общие сведения'!$D$2)-1 & " г.", YEAR('Общие сведения'!$D$2)-1 & " г."))) -> за январь-март 2025 г. | M32: =D32+F32+G32+I32+K32 -> 0 | N32: =E32+H32+J32+L32 -> 0 | P32: год
A33: прочие долгосрочные финансовые вложения | B33: 60 | C33: ="за " & IF(MONTH('Общие сведения'!D2)=3, "январь-март " & YEAR('Общие сведения'!D2) & " г.", IF(MONTH('Общие сведения'!D2)=6, "январь-июнь " & YEAR('Общие сведения'!D2) & " г.", IF(MONTH('Общие сведения'!D2)=9, "январь-сентябрь " & YEAR('Общие сведения'!D2) & " г.", YEAR('Общие сведения'!D2) & " г."))) -> за январь-март 2026 г. | M33: =D33+F33+G33+I33+K33 -> 0 | N33: =E33+H33+J33+L33 -> 0
B34: 61 | C34: ="за " & IF(MONTH('Общие сведения'!$D$2)=3, "январь-март " & YEAR('Общие сведения'!$D$2)-1 & " г.", IF(MONTH('Общие сведения'!$D$2)=6, "январь-июнь " & YEAR('Общие сведения'!$D$2)-1 & " г.", IF(MONTH('Общие сведения'!$D$2)=9, "январь-сентябрь " & YEAR('Общие сведения'!$D$2)-1 & " г.", YEAR('Общие сведения'!$D$2)-1 & " г."))) -> за январь-март 2025 г. | M34: =D34+F34+G34+I34+K34 -> 0 | N34: =E34+H34+J34+L34 -> 0
A35: Краткосрочные финансовые вложения - всего | B35: 70 | C35: ="за " & IF(MONTH('Общие сведения'!D2)=3, "январь-март " & YEAR('Общие сведения'!D2) & " г.", IF(MONTH('Общие сведения'!D2)=6, "январь-июнь " & YEAR('Общие сведения'!D2) & " г.", IF(MONTH('Общие сведения'!D2)=9, "январь-сентябрь " & YEAR('Общие сведения'!D2) & " г.", YEAR('Общие сведения'!D2) & " г."))) -> за январь-март 2026 г. | D35: =D39+D41 -> 0 | E35: =E39+E41 -> 0 | F35: =F39+F41 -> 0 | G35: =G39+G41 -> 0 | H35: =H39+H41 -> 0 | I35: =I39+I41 -> 0 | J35: =J39+J41 -> 0 | K35: =K39+K41 -> 0 | ... N35: =N39+N41 -> 0
B36: 71 | C36: ="за " & IF(MONTH('Общие сведения'!$D$2)=3, "январь-март " & YEAR('Общие сведения'!$D$2)-1 & " г.", IF(MONTH('Общие сведения'!$D$2)=6, "январь-июнь " & YEAR('Общие сведения'!$D$2)-1 & " г.", IF(MONTH('Общие сведения'!$D$2)=9, "январь-сентябрь " & YEAR('Общие сведения'!$D$2)-1 & " г.", YEAR('Общие сведения'!$D$2)-1 & " г."))) -> за январь-март 2025 г. | D36: =D40+D42 -> 0 | E36: =E40+E42 -> 0 | F36: =F40+F42 -> 0 | G36: =G40+G42 -> 0 | H36: =H40+H42 -> 0 | I36: =I40+I42 -> 0 | J36: =J40+J42 -> 0 | K36: =K40+K42 -> 0 | ... N36: =N40+N42 -> 0 | P36: год
A37: в том числе:
A38: --- | C38: резерв | M38: =D38+F38+G38+I38 -> 0 | N38: =E38+H38+J38 -> 0 | P38: резерв
A39: займы выданные | B39: 80 | C39: ="за " & IF(MONTH('Общие сведения'!D2)=3, "январь-март " & YEAR('Общие сведения'!D2) & " г.", IF(MONTH('Общие сведения'!D2)=6, "январь-июнь " & YEAR('Общие сведения'!D2) & " г.", IF(MONTH('Общие сведения'!D2)=9, "январь-сентябрь " & YEAR('Общие сведения'!D2) & " г.", YEAR('Общие сведения'!D2) & " г."))) -> за январь-март 2026 г. | M39: =D39+F39+G39+I39+K39 -> 0 | N39: =E39+H39+J39+L39 -> 0
B40: 81 | C40: ="за " & IF(MONTH('Общие сведения'!$D$2)=3, "январь-март " & YEAR('Общие сведения'!$D$2)-1 & " г.", IF(MONTH('Общие сведения'!$D$2)=6, "январь-июнь " & YEAR('Общие сведения'!$D$2)-1 & " г.", IF(MONTH('Общие сведения'!$D$2)=9, "январь-сентябрь " & YEAR('Общие сведения'!$D$2)-1 & " г.", YEAR('Общие сведения'!$D$2)-1 & " г."))) -> за январь-март 2025 г. | M40: =D40+F40+G40+I40+K40 -> 0 | N40: =E40+H40+J40+L40 -> 0 | P40: год
A41: прочие краткосрочные финансовые вложения | B41: 90 | C41: ="за " & IF(MONTH('Общие сведения'!D2)=3, "январь-март " & YEAR('Общие сведения'!D2) & " г.", IF(MONTH('Общие сведения'!D2)=6, "январь-июнь " & YEAR('Общие сведения'!D2) & " г.", IF(MONTH('Общие сведения'!D2)=9, "январь-сентябрь " & YEAR('Общие сведения'!D2) & " г.", YEAR('Общие сведения'!D2) & " г."))) -> за январь-март 2026 г. | M41: =D41+F41+G41+I41+K41 -> 0 | N41: =E41+H41+J41+L41 -> 0
B42: 91 | C42: ="за " & IF(MONTH('Общие сведения'!$D$2)=3, "январь-март " & YEAR('Общие сведения'!$D$2)-1 & " г.", IF(MONTH('Общие сведения'!$D$2)=6, "январь-июнь " & YEAR('Общие сведения'!$D$2)-1 & " г.", IF(MONTH('Общие сведения'!$D$2)=9, "январь-сентябрь " & YEAR('Общие сведения'!$D$2)-1 & " г.", YEAR('Общие сведения'!$D$2)-1 & " г."))) -> за январь-март 2025 г. | M42: =D42+F42+G42+I42+K42 -> 0 | N42: =E42+H42+J42+L42 -> 0 | P42: год
A43: Финансовых вложений - всего | B43: 100 | C43: ="за " & IF(MONTH('Общие сведения'!D2)=3, "январь-март " & YEAR('Общие сведения'!D2) & " г.", IF(MONTH('Общие сведения'!D2)=6, "январь-июнь " & YEAR('Общие сведения'!D2) & " г.", IF(MONTH('Общие сведения'!D2)=9, "январь-сентябрь " & YEAR('Общие сведения'!D2) & " г.", YEAR('Общие сведения'!D2) & " г."))) -> за январь-март 2026 г. | D43: =D22+D35 -> 0 | E43: =E22+E35 -> 0 | F43: =F22+F35 -> 0 | G43: =G22+G35 -> 0 | H43: =H22+H35 -> 0 | I43: =I22+I35 -> 0 | J43: =J22+J35 -> 0 | K43: =K22+K35 -> 0 | L43: =L22+L35 -> 0 | M43: =D43+F43+G43+I43+K43 -> 0 | N43: =E43+H43+J43+L43 -> 0
B44: 101 | C44: ="за " & IF(MONTH('Общие сведения'!$D$2)=3, "январь-март " & YEAR('Общие сведения'!$D$2)-1 & " г.", IF(MONTH('Общие сведения'!$D$2)=6, "январь-июнь " & YEAR('Общие сведения'!$D$2)-1 & " г.", IF(MONTH('Общие сведения'!$D$2)=9, "январь-сентябрь " & YEAR('Общие сведения'!$D$2)-1 & " г.", YEAR('Общие сведения'!$D$2)-1 & " г."))) -> за январь-март 2025 г. | D44: =D23+D36 -> 0 | E44: =E23+E36 -> 0 | F44: =F23+F36 -> 0 | G44: =G23+G36 -> 0 | H44: =H23+H36 -> 0 | I44: =I23+I36 -> 0 | J44: =J23+J36 -> 0 | K44: =K23+K36 -> 0 | L44: =L23+L36 -> 0 | M44: =D44+F44+G44+I44+K44 -> 0 | N44: =E44+H44+J44+L44 -> 0 | P44: год

Sheet 5.3.2
F2: Коды
F3: 0710001
E4: Дата(число,месяц,год) .
A5: Организация | E5: по ОКПО .
A6: Идентификационный номер налогоплательщика | E6: ИНН .
A7: Вид экономической деятельности | E7: по ОКВЭД .
A8: Организационно-правовая форма / форма собственности
E9: по ОКОПФ/ОКФС .
A10: Единица измерения: тыс.руб. | E10: по ОКЕИ . | F10: 384
A11: Местонахождение (адрес)
H12: с.9 | J12: с.9
A13: 3.2 Иное использование финансовых вложений
A14: Единица измерения: тыс.руб.
A15: Наименование показателя | D15: Код АСКО | E15: ="на " & DAY('Общие сведения'!$D$2) & CHOOSE(MONTH('Общие сведения'!$D$2), " января ", " февраля ", " марта ", " апреля ", " мая ", " июня ", " июля ", " августа ", " сентября ", " октября ", " ноября ", " декабря ") & " " & YEAR('Общие сведения'!$D$2) & " г." -> на 31 марта 2026 г. | G15: ="на 31 декабря " & YEAR('Общие сведения'!$D$2)-1 & " г." -> на 31 декабря 2025 г. | I15: ="на 31 декабря " & YEAR('Общие сведения'!$D$2)-2 & " г." -> на 31 декабря 2024 г.
A16: Код АСКО | E16: E | F16: F | G16: G | H16: H
A17: Долгосрочные финансовые вложения, находящиеся в залоге, - всего | D17: 10 | E17: =SUM(E19:F22) -> 0 | G17: =SUM(G19:H22) -> 0 | I17: =SUM(I19:J22) -> 0
A18: в том числе:
A19: инвестиции в дочерние общества | D19: 20
A20: инвестиции в зависимые общества | D20: 30
A21: инвестиции в другие организации | D21: 40
A22: прочие долгосрочные финансовые вложения | D22: 50
A23: Долгосрочные финансовые вложения, переданные третьим лицам (кроме продажи), - всего | D23: 60 | E23: =SUM(E25:F28) -> 0 | G23: =SUM(G25:H28) -> 0 | I23: =SUM(I25:J28) -> 0
A24: в том числе:
A25: инвестиции в дочерние общества | D25: 70
A26: инвестиции в зависимые общества | D26: 80
A27: инвестиции в другие организации | D27: 90
A28: прочие долгосрочные финансовые вложения | D28: 100
A29: Краткосрочные финансовые вложения, находящиеся в залоге | D29: 110
A30: Краткосрочные финансовые вложения, переданные третьим лицам (кроме продажи) | D30: 120

Sheet 5.4.1 5.4.2
M13: с.10
B14: 4. Запасы
B15: 4.1 Наличие и движение запасов
B16: Единица измерения: тыс.руб.
A18: Код АСКО | B18: Наименование показателя | C18: Период | D18: На начало года | F18: Изменения за период | L18: На конец периода
D19: фактическая себестоимость | E19: величина резерва под обесценение | F19: поступление и затраты | G19: выбыло | I19: обесценение | J19: оборот запасов между их группами (видами) | L19: фактическая себестоимость | M19: величина резерва под обесценение
G20: фактическая себестоимость | H20: резерв под обесценение | J20: фактическая себестоимость | K20: резерв под обесценение
B21: Код АСКО | D21: D | E21: E | F21: F | G21: G | H21: H | I21: I | J21: J | K21: K | L21: L | M21: M | O21: годовые
A22: 10 | B22: Запасы - всего | C22: ="за " & IF(MONTH('Общие сведения'!D2)=3, "январь-март " & YEAR('Общие сведения'!D2) & " г.", IF(MONTH('Общие сведения'!D2)=6, "январь-июнь " & YEAR('Общие сведения'!D2) & " г.", IF(MONTH('Общие сведения'!D2)=9, "январь-сентябрь " & YEAR('Общие сведения'!D2) & " г.", YEAR('Общие сведения'!D2) & " г."))) -> за январь-март 2026 г. | D22: =D25+D27+D29+D31+D33 -> 0 | E22: =E25+E27+E29+E31+E33 -> 0 | F22: =F25+F27+F29+F31+F33 -> 0 | G22: =G25+G27+G29+G31+G33 -> 0 | H22: =H25+H27+H29+H31+H33 -> 0 | I22: =I25+I27+I29+I31+I33 -> 0 | J22: =J25+J27+J29+J31+J33 -> 0 | K22: =K25+K27+K29+K31+K33 -> 0 | ... M22: =M25+M27+M29+M31+M33 -> 0
A23: 20 | C23: ="за " & IF(MONTH('Общие сведения'!$D$2)=3, "январь-март " & YEAR('Общие сведения'!$D$2)-1 & " г.", IF(MONTH('Общие сведения'!$D$2)=6, "январь-июнь " & YEAR('Общие сведения'!$D$2)-1 & " г.", IF(MONTH('Общие сведения'!$D$2)=9, "январь-сентябрь " & YEAR('Общие сведения'!$D$2)-1 & " г.", YEAR('Общие сведения'!$D$2)-1 & " г."))) -> за январь-март 2025 г. | D23: =D26+D28+D30+D32+D34 -> 0 | E23: =E26+E28+E30+E32+E34 -> 0 | F23: =F26+F28+F30+F32+F34 -> 0 | G23: =G26+G28+G30+G32+G34 -> 0 | H23: =H26+H28+H30+H32+H34 -> 0 | I23: =I26+I28+I30+I32+I34 -> 0 | J23: =J26+J28+J30+J32+J34 -> 0 | K23: =K26+K28+K30+K32+K34 -> 0 | ... M23: =M26+M28+M30+M32+M34 -> 0 | O23: год
B24: в том числе:
A25: 30 | B25: сырье, материалы и другие аналогичные ценности | C25: ="за " & IF(MONTH('Общие сведения'!D2)=3, "январь-март " & YEAR('Общие сведения'!D2) & " г.", IF(MONTH('Общие сведения'!D2)=6, "январь-июнь " & YEAR('Общие сведения'!D2) & " г.", IF(MONTH('Общие сведения'!D2)=9, "январь-сентябрь " & YEAR('Общие сведения'!D2) & " г.", YEAR('Общие сведения'!D2) & " г."))) -> за январь-март 2026 г. | L25: =D25+F25+G25+J25 -> 0 | M25: =E25+H25+I25+K25 -> 0
A26: 40 | C26: ="за " & IF(MONTH('Общие сведения'!$D$2)=3, "январь-март " & YEAR('Общие сведения'!$D$2)-1 & " г.", IF(MONTH('Общие сведения'!$D$2)=6, "январь-июнь " & YEAR('Общие сведения'!$D$2)-1 & " г.", IF(MONTH('Общие сведения'!$D$2)=9, "январь-сентябрь " & YEAR('Общие сведения'!$D$2)-1 & " г.", YEAR('Общие сведения'!$D$2)-1 & " г."))) -> за январь-март 2025 г. | L26: =D26+F26+G26+J26 -> 0 | M26: =E26+H26+I26+K26 -> 0 | O26: год
O27: резерв
O28: резерв
A29: 50 | B29: затраты в незавершенном производстве | C29: ="за " & IF(MONTH('Общие сведения'!D2)=3, "январь-март " & YEAR('Общие сведения'!D2) & " г.", IF(MONTH('Общие сведения'!D2)=6, "январь-июнь " & YEAR('Общие сведения'!D2) & " г.", IF(MONTH('Общие сведения'!D2)=9, "январь-сентябрь " & YEAR('Общие сведения'!D2) & " г.", YEAR('Общие сведения'!D2) & " г."))) -> за январь-март 2026 г. | L29: =D29+F29+G29+J29 -> 0 | M29: =E29+H29+I29+K29 -> 0
A30: 60 | C30: ="за " & IF(MONTH('Общие сведения'!$D$2)=3, "январь-март " & YEAR('Общие сведения'!$D$2)-1 & " г.", IF(MONTH('Общие сведения'!$D$2)=6, "январь-июнь " & YEAR('Общие сведения'!$D$2)-1 & " г.", IF(MONTH('Общие сведения'!$D$2)=9, "январь-сентябрь " & YEAR('Общие сведения'!$D$2)-1 & " г.", YEAR('Общие сведения'!$D$2)-1 & " г."))) -> за январь-март 2025 г. | L30: =D30+F30+G30+J30 -> 0 | M30: =E30+H30+I30+K30 -> 0 | O30: год
A31: 70 | B31: готовая продукция и товары для перепродажи | C31: ="за " & IF(MONTH('Общие сведения'!D2)=3, "январь-март " & YEAR('Общие сведения'!D2) & " г.", IF(MONTH('Общие сведения'!D2)=6, "январь-июнь " & YEAR('Общие сведения'!D2) & " г.", IF(MONTH('Общие сведения'!D2)=9, "январь-сентябрь " & YEAR('Общие сведения'!D2) & " г.", YEAR('Общие сведения'!D2) & " г."))) -> за январь-март 2026 г. | L31: =D31+F31+G31+J31 -> 0 | M31: =E31+H31+I31+K31 -> 0
A32: 80 | C32: ="за " & IF(MONTH('Общие сведения'!$D$2)=3, "январь-март " & YEAR('Общие сведения'!$D$2)-1 & " г.", IF(MONTH('Общие сведения'!$D$2)=6, "январь-июнь " & YEAR('Общие сведения'!$D$2)-1 & " г.", IF(MONTH('Общие сведения'!$D$2)=9, "январь-сентябрь " & YEAR('Общие сведения'!$D$2)-1 & " г.", YEAR('Общие сведения'!$D$2)-1 & " г."))) -> за январь-март 2025 г. | L32: =D32+F32+G32+J32 -> 0 | M32: =E32+H32+I32+K32 -> 0 | O32: год
A33: 90 | B33: товары отгруженные | C33: ="за " & IF(MONTH('Общие сведения'!D2)=3, "январь-март " & YEAR('Общие сведения'!D2) & " г.", IF(MONTH('Общие сведения'!D2)=6, "январь-июнь " & YEAR('Общие сведения'!D2) & " г.", IF(MONTH('Общие сведения'!D2)=9, "январь-сентябрь " & YEAR('Общие сведения'!D2) & " г.", YEAR('Общие сведения'!D2) & " г."))) -> за январь-март 2026 г. | L33: =D33+F33+G33+J33 -> 0 | M33: =E33+H33+I33+K33 -> 0
A34: 100 | C34: ="за " & IF(MONTH('Общие сведения'!$D$2)=3, "январь-март " & YEAR('Общие сведения'!$D$2)-1 & " г.", IF(MONTH('Общие сведения'!$D$2)=6, "январь-июнь " & YEAR('Общие сведения'!$D$2)-1 & " г.", IF(MONTH('Общие сведения'!$D$2)=9, "январь-сентябрь " & YEAR('Общие сведения'!$D$2)-1 & " г.", YEAR('Общие сведения'!$D$2)-1 & " г."))) -> за январь-март 2025 г. | L34: =D34+F34+G34+J34 -> 0 | M34: =E34+H34+I34+K34 -> 0 | O34: год
B38: 4.2 Запасы, в отношении которых имеются ограничения имущественных прав
B39: Единица измерения: тыс.руб.
B40: Наименование показателя | D40: ="на " & DAY('Общие сведения'!$D$2) & CHOOSE(MONTH('Общие сведения'!$D$2), " января ", " февраля ", " марта ", " апреля ", " мая ", " июня ", " июля ", " августа ", " сентября ", " октября ", " ноября ", " декабря ") & " " & YEAR('Общие сведения'!$D$2) & " г." -> на 31 марта 2026 г. | F40: ="на 31 декабря " & YEAR('Общие сведения'!$D$2)-1 & " г." -> на 31 декабря 2025 г. | H40: ="на 31 декабря " & YEAR('Общие сведения'!$D$2)-2 & " г." -> на 31 декабря 2024 г.
A41: 110 | B41: Запасы, в отношении которых имеются ограничения имущественных прав, в том числе находящиеся в залоге | D41: =D43+D46 -> 0 | F41: =F43+F46 -> 0 | H41: =H43+H46 -> 0
B42: в том числе:
A43: 120 | B43: сырье, материалы и другие аналогичные ценности
A44: 130 | B44: животные на выращивании и откорме | O44: резерв
A45: 140 | B45: затраты в незавершенном производстве | O45: резерв
A46: 150 | B46: готовая продукция и товары для перепродажи

Sheet 5.5
F2: Коды
F3: 0710001
E4: Дата(число,месяц,год) .
A5: Организация | E5: по ОКПО .
A6: Идентификационный номер налогоплательщика | E6: ИНН .
A7: Вид экономической деятельности | E7: по ОКВЭД .
A8: Организационно-правовая форма / форма собственности
E9: по ОКОПФ/ОКФС .
A10: Единица измерения: тыс.руб. | E10: по ОКЕИ . | F10: 384
A11: Местонахождение (адрес)
G12: с.11
A13: 5. Затраты на производство
A14: Единица измерения: тыс.руб.
A15: Наименование показателя | C15: Код АСКО | D15: ="За " & IF(MONTH('Общие сведения'!D2)=3, "январь-март " & YEAR('Общие сведения'!D2) & " г.", IF(MONTH('Общие сведения'!D2)=6, "январь-июнь " & YEAR('Общие сведения'!D2) & " г.", IF(MONTH('Общие сведения'!D2)=9, "январь-сентябрь " & YEAR('Общие сведения'!D2) & " г.", YEAR('Общие сведения'!D2) & " г."))) -> За январь-март 2026 г. | F15: ="За " & IF(MONTH('Общие сведения'!D2)=3, "январь-март " & YEAR('Общие сведения'!D2)-1 & " г.", IF(MONTH('Общие сведения'!D2)=6, "январь-июнь " & YEAR('Общие сведения'!D2)-1 & " г.", IF(MONTH('Общие сведения'!D2)=9, "январь-сентябрь " & YEAR('Общие сведения'!D2)-1 & " г.", YEAR('Общие сведения'!D2)-1 & " г."))) -> За январь-март 2025 г.
A16: Код АСКО | D16: D | E16: E | F16: F | G16: G
A17: Материальные затраты | C17: 10
A18: Затраты на оплату отруда | C18: 20
A19: Отчисления на социальные нужды | C19: 30
A20: Амортизация | C20: 40
A21: Прочие затраты | C21: 50
A22: Итого по элементам | C22: 60
A23: Изменение остатков незавершенного производства, готовой продукции и др. (прирост [ - ], уменьшение (+)) | C23: 70
A24: Итого расходы по обычным видам деятельности | C24: 80

Sheet 5.6
F2: Коды
F3: 0710001
E4: Дата(число,месяц,год) .
A5: Организация | E5: по ОКПО .
A6: Идентификационный номер налогоплательщика | E6: ИНН .
A7: Вид экономической деятельности | E7: по ОКВЭД .
A8: Организационно-правовая форма / форма собственности
E9: по ОКОПФ/ОКФС .
A10: Единица измерения: тыс.руб. | E10: по ОКЕИ . | F10: 384
I11: с.12
A12: 6. Оценочные обязательства
A13: Единица измерения: тыс.руб.
A14: Наименование показателя | B14: Код АСКО | C14: Период | D14: Остаток на начало года | E14: Начислено | F14: Использовано | G14: Восстановлено | H14: Остаток на конец периода
A15: Код АСКО | D15: D | E15: E | F15: F | G15: G | H15: H
A16: Оценочные обязательства - всего | B16: 5 | C16: ="за " & IF(MONTH('Общие сведения'!D2)=3, "январь-март " & YEAR('Общие сведения'!D2) & " г.", IF(MONTH('Общие сведения'!D2)=6, "январь-июнь " & YEAR('Общие сведения'!D2) & " г.", IF(MONTH('Общие сведения'!D2)=9, "январь-сентябрь " & YEAR('Общие сведения'!D2) & " г.", YEAR('Общие сведения'!D2) & " г."))) -> за январь-март 2026 г. | D16: =D18+D20+D22+D24+D26+D28 -> 0 | E16: =E18+E20+E22+E24+E26+E28 -> 0 | F16: =F18+F20+F22+F24+F26+F28 -> 0 | G16: =G18+G20+G22+G24+G26+G28 -> 0 | H16: =D16+E16+F16+G16 -> 0
C17: ="за " & IF(MONTH('Общие сведения'!D2)=3, "3 мес. " & YEAR('Общие сведения'!D2)-1 & " г.", IF(MONTH('Общие сведения'!D2)=12, YEAR('Общие сведения'!D2)-1 & " г.",MONTH('Общие сведения'!D2) & " мес. " & YEAR('Общие сведения'!D2)-1 & " г.")) -> за 3 мес. 2025 г. | D17: =D19+D21+D23+D25+D27+D29 -> 0 | E17: =E19+E21+E23+E25+E27+E29 -> 0 | F17: =F19+F21+F23+F25+F27+F29 -> 0 | G17: =G19+G21+G23+G25+G27+G29 -> 0 | H17: =D17+E17+F17+G17 -> 0 | J17: год
A18: обязательства по ликвидации основных средств и восстановлению окружающей среды в связи с пользованием недрами | B18: 10 | C18: ="за " & IF(MONTH('Общие сведения'!D2)=3, "январь-март " & YEAR('Общие сведения'!D2) & " г.", IF(MONTH('Общие сведения'!D2)=6, "январь-июнь " & YEAR('Общие сведения'!D2) & " г.", IF(MONTH('Общие сведения'!D2)=9, "январь-сентябрь " & YEAR('Общие сведения'!D2) & " г.", YEAR('Общие сведения'!D2) & " г."))) -> за январь-март 2026 г. | H18: =D18+E18+F18+G18 -> 0
C19: ="за " & IF(MONTH('Общие сведения'!D2)=3, "3 мес. " & YEAR('Общие сведения'!D2)-1 & " г.", IF(MONTH('Общие сведения'!D2)=12, YEAR('Общие сведения'!D2)-1 & " г.",MONTH('Общие сведения'!D2) & " мес. " & YEAR('Общие сведения'!D2)-1 & " г.")) -> за 3 мес. 2025 г. | H19: =D19+E19+F19+G19 -> 0 | J19: год
A20: выданные гарантийные обязательства | B20: 20 | C20: ="за " & IF(MONTH('Общие сведения'!D2)=3, "январь-март " & YEAR('Общие сведения'!D2) & " г.", IF(MONTH('Общие сведения'!D2)=6, "январь-июнь " & YEAR('Общие сведения'!D2) & " г.", IF(MONTH('Общие сведения'!D2)=9, "январь-сентябрь " & YEAR('Общие сведения'!D2) & " г.", YEAR('Общие сведения'!D2) & " г."))) -> за январь-март 2026 г. | H20: =D20+E20+F20+G20 -> 0
C21: ="за " & IF(MONTH('Общие сведения'!D2)=3, "3 мес. " & YEAR('Общие сведения'!D2)-1 & " г.", IF(MONTH('Общие сведения'!D2)=12, YEAR('Общие сведения'!D2)-1 & " г.",MONTH('Общие сведения'!D2) & " мес. " & YEAR('Общие сведения'!D2)-1 & " г.")) -> за 3 мес. 2025 г. | H21: =D21+E21+F21+G21 -> 0 | J21: год
A22: судебные разбирательства | B22: 30 | C22: ="за " & IF(MONTH('Общие сведения'!D2)=3, "январь-март " & YEAR('Общие сведения'!D2) & " г.", IF(MONTH('Общие сведения'!D2)=6, "январь-июнь " & YEAR('Общие сведения'!D2) & " г.", IF(MONTH('Общие сведения'!D2)=9, "январь-сентябрь " & YEAR('Общие сведения'!D2) & " г.", YEAR('Общие сведения'!D2) & " г."))) -> за январь-март 2026 г. | H22: =D22+E22+F22+G22 -> 0
C23: ="за " & IF(MONTH('Общие сведения'!D2)=3, "3 мес. " & YEAR('Общие сведения'!D2)-1 & " г.", IF(MONTH('Общие сведения'!D2)=12, YEAR('Общие сведения'!D2)-1 & " г.",MONTH('Общие сведения'!D2) & " мес. " & YEAR('Общие сведения'!D2)-1 & " г.")) -> за 3 мес. 2025 г. | H23: =D23+E23+F23+G23 -> 0 | J23: год
A24: прочие оценочные обязательства | B24: 40 | C24: ="за " & IF(MONTH('Общие сведения'!D2)=3, "январь-март " & YEAR('Общие сведения'!D2) & " г.", IF(MONTH('Общие сведения'!D2)=6, "январь-июнь " & YEAR('Общие сведения'!D2) & " г.", IF(MONTH('Общие сведения'!D2)=9, "январь-сентябрь " & YEAR('Общие сведения'!D2) & " г.", YEAR('Общие сведения'!D2) & " г."))) -> за январь-март 2026 г. | H24: =D24+E24+F24+G24 -> 0
C25: ="за " & IF(MONTH('Общие сведения'!D2)=3, "3 мес. " & YEAR('Общие сведения'!D2)-1 & " г.", IF(MONTH('Общие сведения'!D2)=12, YEAR('Общие сведения'!D2)-1 & " г.",MONTH('Общие сведения'!D2) & " мес. " & YEAR('Общие сведения'!D2)-1 & " г.")) -> за 3 мес. 2025 г. | H25: =D25+E25+F25+G25 -> 0 | J25: год
A26: обязательство по выплате вознаграждений по итогам работы за год | B26: 50 | C26: ="за " & IF(MONTH('Общие сведения'!D2)=3, "январь-март " & YEAR('Общие сведения'!D2) & " г.", IF(MONTH('Общие сведения'!D2)=6, "январь-июнь " & YEAR('Общие сведения'!D2) & " г.", IF(MONTH('Общие сведения'!D2)=9, "январь-сентябрь " & YEAR('Общие сведения'!D2) & " г.", YEAR('Общие сведения'!D2) & " г."))) -> за январь-март 2026 г. | H26: =D26+E26+F26+G26 -> 0
C27: ="за " & IF(MONTH('Общие сведения'!D2)=3, "3 мес. " & YEAR('Общие сведения'!D2)-1 & " г.", IF(MONTH('Общие сведения'!D2)=12, YEAR('Общие сведения'!D2)-1 & " г.",MONTH('Общие сведения'!D2) & " мес. " & YEAR('Общие сведения'!D2)-1 & " г.")) -> за 3 мес. 2025 г. | H27: =D27+E27+F27+G27 -> 0 | J27: год
A28: обязательство по оплате отпусков | B28: 60 | C28: ="за " & IF(MONTH('Общие сведения'!D2)=3, "январь-март " & YEAR('Общие сведения'!D2) & " г.", IF(MONTH('Общие сведения'!D2)=6, "январь-июнь " & YEAR('Общие сведения'!D2) & " г.", IF(MONTH('Общие сведения'!D2)=9, "январь-сентябрь " & YEAR('Общие сведения'!D2) & " г.", YEAR('Общие сведения'!D2) & " г."))) -> за январь-март 2026 г. | H28: =D28+E28+F28+G28 -> 0
C29: ="за " & IF(MONTH('Общие сведения'!D2)=3, "3 мес. " & YEAR('Общие сведения'!D2)-1 & " г.", IF(MONTH('Общие сведения'!D2)=12, YEAR('Общие сведения'!D2)-1 & " г.",MONTH('Общие сведения'!D2) & " мес. " & YEAR('Общие сведения'!D2)-1 & " г.")) -> за 3 мес. 2025 г. | H29: =D29+E29+F29+G29 -> 0 | J29: год
A30: в т.ч. со сроком погашения до 1 года | B30: 70 | C30: ="за " & IF(MONTH('Общие сведения'!D2)=3, "январь-март " & YEAR('Общие сведения'!D2) & " г.", IF(MONTH('Общие сведения'!D2)=6, "январь-июнь " & YEAR('Общие сведения'!D2) & " г.", IF(MONTH('Общие сведения'!D2)=9, "январь-сентябрь " & YEAR('Общие сведения'!D2) & " г.", YEAR('Общие сведения'!D2) & " г."))) -> за январь-март 2026 г. | E30: - | F30: - | G30: -
C31: ="за " & IF(MONTH('Общие сведения'!D2)=3, "3 мес. " & YEAR('Общие сведения'!D2)-1 & " г.", IF(MONTH('Общие сведения'!D2)=12, YEAR('Общие сведения'!D2)-1 & " г.",MONTH('Общие сведения'!D2) & " мес. " & YEAR('Общие сведения'!D2)-1 & " г.")) -> за 3 мес. 2025 г. | E31: - | F31: - | G31: - | J31: год

Sheet 5.7
E4: Дата(число,месяц,год) .
A5: Организация | E5: по ОКПО .
A6: Идентификационный номер налогоплательщика | E6: ИНН .
A7: Вид экономической деятельности | E7: по ОКВЭД .
A8: Организационно-правовая форма / форма собственности
E9: по ОКОПФ/ОКФС .
A10: Единица измерения: тыс.руб. | E10: по ОКЕИ .
A11: Местонахождение (адрес)
O14: с.13
A15: 7. Наличие и движение поисковых активов
A16: Единица измерения: тыс.руб.
A17: Наименование показателя | B17: Код АСКО | C17: Период | D17: На начало года | F17: Изменения за период | N17: На конец периода
D18: первоначаль-ная (фактическая) стоимость | E18: накоплен-ные аморти-зация и обесцене-ние | F18: поступило | H18: выбыло объектов | J18: начислено амортизации | K18: обесценение | L18: переклассификация, в т.ч. в долгосрочные активы к продаже | N18: первоначаль-ная (фактическая) стоимость | O18: накоплен-ные амортиза-ция и обесцене-ние
F19: первоначальная (фактическая) стоимость | G19: накопленные амортизация и обесценение | H19: первоначальная (фактическая) стоимость | I19: накопленные амортизация и обесценение | L19: первоначальная (фактическая) стоимость | M19: накопленные амортизация и обесценение
A20: Код АСКО | D20: D | E20: E | F20: F | G20: G | H20: H | I20: I | J20: J | K20: K | L20: L | M20: M | N20: N | O20: O
A21: Нематериальные поисковые активы - всего | B21: 5 | C21: ="за " & IF(MONTH('Общие сведения'!D2)=3, "январь-март " & YEAR('Общие сведения'!D2) & " г.", IF(MONTH('Общие сведения'!D2)=6, "январь-июнь " & YEAR('Общие сведения'!D2) & " г.", IF(MONTH('Общие сведения'!D2)=9, "январь-сентябрь " & YEAR('Общие сведения'!D2) & " г.", YEAR('Общие сведения'!D2) & " г."))) -> за январь-март 2026 г. | D21: =D25+D27 -> 0 | E21: =E25+E27 -> 0 | F21: =F25+F27 -> 0 | G21: =G25+G27 -> 0 | H21: =H25+H27 -> 0 | I21: =I25+I27 -> 0 | J21: =J25+J27 -> 0 | K21: =K25+K27 -> 0 | ... O21: =O25+O27 -> 0
C22: ="за " & IF(MONTH('Общие сведения'!D2)=3, "3 мес. " & YEAR('Общие сведения'!D2)-1 & " г.", IF(MONTH('Общие сведения'!D2)=12, YEAR('Общие сведения'!D2)-1 & " г.",MONTH('Общие сведения'!D2) & " мес. " & YEAR('Общие сведения'!D2)-1 & " г.")) -> за 3 мес. 2025 г. | D22: =D26+D28 -> 0 | E22: =E26+E28 -> 0 | F22: =F26+F28 -> 0 | G22: =G26+G28 -> 0 | H22: =H26+H28 -> 0 | I22: =I26+I28 -> 0 | J22: =J26+J28 -> 0 | K22: =K26+K28 -> 0 | ... O22: =O26+O28 -> 0 | Q22: год
A23: в том числе:
A25: лицензии | B25: 10 | C25: ="за " & IF(MONTH('Общие сведения'!D2)=3, "январь-март " & YEAR('Общие сведения'!D2) & " г.", IF(MONTH('Общие сведения'!D2)=6, "январь-июнь " & YEAR('Общие сведения'!D2) & " г.", IF(MONTH('Общие сведения'!D2)=9, "январь-сентябрь " & YEAR('Общие сведения'!D2) & " г.", YEAR('Общие сведения'!D2) & " г."))) -> за январь-март 2026 г. | N25: =D25+F25+H25+L25 -> 0 | O25: =E25+G25+I25+J25+K25+M25 -> 0
C26: ="за " & IF(MONTH('Общие сведения'!D2)=3, "3 мес. " & YEAR('Общие сведения'!D2)-1 & " г.", IF(MONTH('Общие сведения'!D2)=12, YEAR('Общие сведения'!D2)-1 & " г.",MONTH('Общие сведения'!D2) & " мес. " & YEAR('Общие сведения'!D2)-1 & " г.")) -> за 3 мес. 2025 г. | N26: =D26+F26+H26+L26 -> 0 | O26: =E26+G26+I26+J26+K26+M26 -> 0 | Q26: год
A27: прочие | B27: 20 | C27: ="за " & IF(MONTH('Общие сведения'!D2)=3, "январь-март " & YEAR('Общие сведения'!D2) & " г.", IF(MONTH('Общие сведения'!D2)=6, "январь-июнь " & YEAR('Общие сведения'!D2) & " г.", IF(MONTH('Общие сведения'!D2)=9, "январь-сентябрь " & YEAR('Общие сведения'!D2) & " г.", YEAR('Общие сведения'!D2) & " г."))) -> за январь-март 2026 г. | N27: =D27+F27+H27+L27 -> 0 | O27: =E27+G27+I27+J27+K27+M27 -> 0
C28: ="за " & IF(MONTH('Общие сведения'!D2)=3, "3 мес. " & YEAR('Общие сведения'!D2)-1 & " г.", IF(MONTH('Общие сведения'!D2)=12, YEAR('Общие сведения'!D2)-1 & " г.",MONTH('Общие сведения'!D2) & " мес. " & YEAR('Общие сведения'!D2)-1 & " г.")) -> за 3 мес. 2025 г. | N28: =D28+F28+H28+L28 -> 0 | O28: =E28+G28+I28+J28+K28+M28 -> 0 | Q28: год
A29: Материальные поисковые активы - всего | B29: 55 | C29: ="за " & IF(MONTH('Общие сведения'!D2)=3, "январь-март " & YEAR('Общие сведения'!D2) & " г.", IF(MONTH('Общие сведения'!D2)=6, "январь-июнь " & YEAR('Общие сведения'!D2) & " г.", IF(MONTH('Общие сведения'!D2)=9, "январь-сентябрь " & YEAR('Общие сведения'!D2) & " г.", YEAR('Общие сведения'!D2) & " г."))) -> за январь-март 2026 г. | D29: =D31+D33+D35+D37 -> 0 | E29: =E31+E33+E35+E37 -> 0 | F29: =F31+F33+F35+F37 -> 0 | G29: =G31+G33+G35+G37 -> 0 | H29: =H31+H33+H35+H37 -> 0 | I29: =I31+I33+I35+I37 -> 0 | J29: =J31+J33+J35+J37 -> 0 | K29: =K31+K33+K35+K37 -> 0 | ... M29: =M31+M33+M35+M37 -> 0 | N29: =D29+F29+H29+L29 -> 0 | O29: =E29+G29+I29+J29+K29+M29 -> 0
C30: ="за " & IF(MONTH('Общие сведения'!D2)=3, "3 мес. " & YEAR('Общие сведения'!D2)-1 & " г.", IF(MONTH('Общие сведения'!D2)=12, YEAR('Общие сведения'!D2)-1 & " г.",MONTH('Общие сведения'!D2) & " мес. " & YEAR('Общие сведения'!D2)-1 & " г.")) -> за 3 мес. 2025 г. | D30: =D32+D34+D36+D38 -> 0 | E30: =E32+E34+E36+E38 -> 0 | F30: =F32+F34+F36+F38 -> 0 | G30: =G32+G34+G36+G38 -> 0 | H30: =H32+H34+H36+H38 -> 0 | I30: =I32+I34+I36+I38 -> 0 | J30: =J32+J34+J36+J38 -> 0 | K30: =K32+K34+K36+K38 -> 0 | ... M30: =M32+M34+M36+M38 -> 0 | N30: =D30+F30+H30+L30 -> 0 | O30: =E30+G30+I30+J30+K30+M30 -> 0 | Q30: год
A31: здания и дороги | B31: 60 | C31: ="за " & IF(MONTH('Общие сведения'!D2)=3, "январь-март " & YEAR('Общие сведения'!D2) & " г.", IF(MONTH('Общие сведения'!D2)=6, "январь-июнь " & YEAR('Общие сведения'!D2) & " г.", IF(MONTH('Общие сведения'!D2)=9, "январь-сентябрь " & YEAR('Общие сведения'!D2) & " г.", YEAR('Общие сведения'!D2) & " г."))) -> за январь-март 2026 г. | N31: =D31+F31+H31+L31 -> 0 | O31: =E31+G31+I31+J31+K31+M31 -> 0
C32: ="за " & IF(MONTH('Общие сведения'!D2)=3, "3 мес. " & YEAR('Общие сведения'!D2)-1 & " г.", IF(MONTH('Общие сведения'!D2)=12, YEAR('Общие сведения'!D2)-1 & " г.",MONTH('Общие сведения'!D2) & " мес. " & YEAR('Общие сведения'!D2)-1 & " г.")) -> за 3 мес. 2025 г. | N32: =D32+F32+H32+L32 -> 0 | O32: =E32+G32+I32+J32+K32+M32 -> 0 | Q32: год
A33: скважины | B33: 70 | C33: ="за " & IF(MONTH('Общие сведения'!D2)=3, "январь-март " & YEAR('Общие сведения'!D2) & " г.", IF(MONTH('Общие сведения'!D2)=6, "январь-июнь " & YEAR('Общие сведения'!D2) & " г.", IF(MONTH('Общие сведения'!D2)=9, "январь-сентябрь " & YEAR('Общие сведения'!D2) & " г.", YEAR('Общие сведения'!D2) & " г."))) -> за январь-март 2026 г. | N33: =D33+F33+H33+L33 -> 0 | O33: =E33+G33+I33+J33+K33+M33 -> 0
C34: ="за " & IF(MONTH('Общие сведения'!D2)=3, "3 мес. " & YEAR('Общие сведения'!D2)-1 & " г.", IF(MONTH('Общие сведения'!D2)=12, YEAR('Общие сведения'!D2)-1 & " г.",MONTH('Общие сведения'!D2) & " мес. " & YEAR('Общие сведения'!D2)-1 & " г.")) -> за 3 мес. 2025 г. | N34: =D34+F34+H34+L34 -> 0 | O34: =E34+G34+I34+J34+K34+M34 -> 0 | Q34: год
A35: машины и оборудование | B35: 80 | C35: ="за " & IF(MONTH('Общие сведения'!D2)=3, "январь-март " & YEAR('Общие сведения'!D2) & " г.", IF(MONTH('Общие сведения'!D2)=6, "январь-июнь " & YEAR('Общие сведения'!D2) & " г.", IF(MONTH('Общие сведения'!D2)=9, "январь-сентябрь " & YEAR('Общие сведения'!D2) & " г.", YEAR('Общие сведения'!D2) & " г."))) -> за январь-март 2026 г. | N35: =D35+F35+H35+L35 -> 0 | O35: =E35+G35+I35+J35+K35+M35 -> 0
C36: ="за " & IF(MONTH('Общие сведения'!D2)=3, "3 мес. " & YEAR('Общие сведения'!D2)-1 & " г.", IF(MONTH('Общие сведения'!D2)=12, YEAR('Общие сведения'!D2)-1 & " г.",MONTH('Общие сведения'!D2) & " мес. " & YEAR('Общие сведения'!D2)-1 & " г.")) -> за 3 мес. 2025 г. | N36: =D36+F36+H36+L36 -> 0 | O36: =E36+G36+I36+J36+K36+M36 -> 0 | Q36: год
A37: прочие ОС | B37: 90 | C37: ="за " & IF(MONTH('Общие сведения'!D2)=3, "январь-март " & YEAR('Общие сведения'!D2) & " г.", IF(MONTH('Общие сведения'!D2)=6, "январь-июнь " & YEAR('Общие сведения'!D2) & " г.", IF(MONTH('Общие сведения'!D2)=9, "январь-сентябрь " & YEAR('Общие сведения'!D2) & " г.", YEAR('Общие сведения'!D2) & " г."))) -> за январь-март 2026 г. | N37: =D37+F37+H37+L37 -> 0 | O37: =E37+G37+I37+J37+K37+M37 -> 0
C38: ="за " & IF(MONTH('Общие сведения'!D2)=3, "3 мес. " & YEAR('Общие сведения'!D2)-1 & " г.", IF(MONTH('Общие сведения'!D2)=12, YEAR('Общие сведения'!D2)-1 & " г.",MONTH('Общие сведения'!D2) & " мес. " & YEAR('Общие сведения'!D2)-1 & " г.")) -> за 3 мес. 2025 г. | N38: =D38+F38+H38+L38 -> 0 | O38: =E38+G38+I38+J38+K38+M38 -> 0 | Q38: год

Sheet 5.8
F2: Коды
F3: 0710001
E4: Дата(число,месяц,год) .
A5: Организация | E5: по ОКПО .
A6: Идентификационный номер налогоплательщика | E6: ИНН .
A7: Вид экономической деятельности | E7: по ОКВЭД .
A8: Организационно-правовая форма / форма собственности
E9: по ОКОПФ/ОКФС .
A10: Единица измерения: тыс.руб. | E10: по ОКЕИ . | F10: 384
A11: Местонахождение (адрес)
G12: с.14 | I12: с.14
A13: 8. Капитальные вложения в поисковые активы
A14: Единица измерения: тыс.руб.
A15: Наименование показателя | C15: Код АСКО | D15: ="на " & DAY('Общие сведения'!$D$2) & CHOOSE(MONTH('Общие сведения'!$D$2), " января ", " февраля ", " марта ", " апреля ", " мая ", " июня ", " июля ", " августа ", " сентября ", " октября ", " ноября ", " декабря ") & " " & YEAR('Общие сведения'!$D$2) & " г." -> на 31 марта 2026 г. | F15: ="на 31 декабря " & YEAR('Общие сведения'!$D$2)-1 & " г." -> на 31 декабря 2025 г. | H15: ="на 31 декабря " & YEAR('Общие сведения'!$D$2)-2 & " г." -> на 31 декабря 2024 г.
D16: первоначальные (фактические) затраты | E16: накопленное обесценение | F16: первоначальные (фактические) затраты | G16: накопленное обесценение | H16: первоначальные (фактические) затраты | I16: накопленное обесценение
A17: Код АСКО | D17: D | E17: E | F17: F | G17: G
A18: Поисковые затраты, учтенные в составе нематериальных поисковых активов | C18: 10
A19: Поисковые затраты, учтенные в составе материальных поисковых активов | C19: 20
A21: ='Общие сведения'!B34 -> Наим. должности (Генеральный директор, Руководитель, ... )
A22: (наименование должности)
F25: ='Общие сведения'!D34 -> 0
A26: (подпись) | F26: (расшифровка подписи)
A28: "_____" ________________________ 2026 г.
